{
  "format_name": "gen6vgc2014",
  "elo_cutoff": 0,
  "pokemon": [
    {
      "pokemon_name": "Abomasnow-Mega",
      "usage_count": 6,
      "usage_pct": 14.29,
      "viability_json": [
        1,
        74,
        74,
        74
      ],
      "abilities_json": {
        "snowwarning": 6.0
      },
      "items_json": {
        "abomasite": 6.0
      },
      "spreads_json": {
        "Quiet:252/4/0/252/0/0": 6.0
      },
      "moves_json": {
        "blizzard": 6.0,
        "protect": 6.0,
        "iceshard": 6.0,
        "energyball": 6.0
      },
      "tera_json": {
        "nothing": 6.0
      },
      "happiness_json": {
        "255": 6.0
      },
      "teammates_json": {
        "Chandelure": 6.0,
        "Conkeldurr": 6.0,
        "Aerodactyl": 6.0,
        "Garchomp": 6.0,
        "Greninja": 6.0
      },
      "counters_json": {}
    },
    {
      "pokemon_name": "Aegislash",
      "usage_count": 12,
      "usage_pct": 26.19,
      "viability_json": [
        5,
        55,
        55,
        55
      ],
      "abilities_json": {
        "stancechange": 12.0
      },
      "items_json": {
        "nothing": 3.0,
        "leftovers": 4.0,
        "weaknesspolicy": 5.0
      },
      "spreads_json": {
        "Adamant:252/252/4/0/0/0": 3.0,
        "Modest:252/0/0/252/4/0": 4.0,
        "Sassy:252/4/4/92/156/0": 2.0,
        "Quiet:212/0/124/0/172/0": 2.0,
        "Quiet:252/4/4/92/156/0": 1.0
      },
      "moves_json": {
        "kingsshield": 12.0,
        "swordsdance": 3.0,
        "gyroball": 3.0,
        "shadowsneak": 5.0,
        "flashcannon": 4.0,
        "shadowball": 9.0,
        "wideguard": 6.0,
        "sacredsword": 5.0,
        "substitute": 1.0
      },
      "tera_json": {
        "nothing": 12.0
      },
      "happiness_json": {
        "255": 12.0
      },
      "teammates_json": {
        "Kangaskhan-Mega": 4.0,
        "Talonflame": 4.0,
        "Greninja": 2.0,
        "Smeargle": 2.0,
        "Hydreigon": 3.0,
        "Lucario-Mega": 4.0,
        "Scrafty": 4.0,
        "Amoonguss": 4.0,
        "Gigalith": 4.0,
        "Reuniclus": 4.0,
        "Rotom-Wash": 2.0,
        "Salamence": 2.0,
        "Garchomp": 2.0,
        "Mawile-Mega": 3.0,
        "Garchomp-Mega": 2.0,
        "Rotom-Heat": 2.0,
        "Zapdos": 3.0,
        "Tyranitar": 3.0,
        "Conkeldurr": 1.0
      },
      "counters_json": {}
    },
    {
      "pokemon_name": "Aerodactyl",
      "usage_count": 10,
      "usage_pct": 23.81,
      "viability_json": [
        2,
        74,
        74,
        74
      ],
      "abilities_json": {
        "rockhead": 4.0,
        "unnerve": 6.0
      },
      "items_json": {
        "focussash": 10.0
      },
      "spreads_json": {
        "Jolly:0/248/0/0/8/252": 4.0,
        "Jolly:0/252/0/0/4/252": 6.0
      },
      "moves_json": {
        "earthquake": 4.0,
        "crunch": 4.0,
        "tailwind": 4.0,
        "rockslide": 10.0,
        "skydrop": 6.0,
        "taunt": 6.0,
        "wideguard": 6.0
      },
      "tera_json": {
        "nothing": 10.0
      },
      "happiness_json": {
        "255": 10.0
      },
      "teammates_json": {
        "Azumarill": 4.0,
        "Garchomp": 10.0,
        "Gengar-Mega": 4.0,
        "Hydreigon": 4.0,
        "Tyranitar": 4.0,
        "Abomasnow-Mega": 6.0,
        "Chandelure": 6.0,
        "Conkeldurr": 6.0,
        "Greninja": 6.0
      },
      "counters_json": {}
    },
    {
      "pokemon_name": "Alakazam-Mega",
      "usage_count": 4,
      "usage_pct": 9.52,
      "viability_json": [
        1,
        38,
        38,
        38
      ],
      "abilities_json": {
        "trace": 4.0
      },
      "items_json": {
        "alakazite": 4.0
      },
      "spreads_json": {
        "Timid:0/0/4/252/0/252": 2.0,
        "Timid:0/0/0/252/4/252": 2.0
      },
      "moves_json": {
        "dazzlinggleam": 4.0,
        "psychic": 4.0,
        "substitute": 2.0,
        "protect": 4.0,
        "safeguard": 2.0
      },
      "tera_json": {
        "nothing": 4.0
      },
      "happiness_json": {
        "255": 4.0
      },
      "teammates_json": {
        "Kangaskhan-Mega": 4.0,
        "Smeargle": 4.0,
        "Talonflame": 4.0,
        "Haxorus": 2.0,
        "Gardevoir": 2.0,
        "Rotom-Wash": 2.0,
        "Garchomp": 2.0
      },
      "counters_json": {}
    },
    {
      "pokemon_name": "Amoonguss",
      "usage_count": 13,
      "usage_pct": 30.95,
      "viability_json": [
        5,
        63,
        63,
        63
      ],
      "abilities_json": {
        "regenerator": 13.0
      },
      "items_json": {
        "rockyhelmet": 3.0,
        "sitrusberry": 4.0,
        "blacksludge": 5.0,
        "ejectbutton": 1.0
      },
      "spreads_json": {
        "Sassy:252/0/180/0/76/0": 6.0,
        "Calm:252/0/180/0/76/0": 4.0,
        "Calm:252/0/0/4/252/0": 2.0,
        "Relaxed:252/0/188/0/68/0": 1.0
      },
      "moves_json": {
        "spore": 11.0,
        "ragepowder": 13.0,
        "gigadrain": 9.0,
        "protect": 13.0,
        "sludgebomb": 4.0,
        "venoshock": 2.0
      },
      "tera_json": {
        "nothing": 13.0
      },
      "happiness_json": {
        "255": 13.0
      },
      "teammates_json": {
        "Mawile-Mega": 8.0,
        "Tyranitar": 3.0,
        "Garchomp": 3.0,
        "Talonflame": 3.0,
        "Zapdos": 3.0,
        "Lucario-Mega": 4.0,
        "Scrafty": 5.0,
        "Aegislash": 4.0,
        "Gigalith": 4.0,
        "Reuniclus": 4.0,
        "Gothitelle": 6.0,
        "Blastoise-Mega": 3.0,
        "Politoed": 4.0,
        "Escavalier": 3.0,
        "Slowking": 2.0,
        "Conkeldurr": 2.0,
        "Clawitzer": 2.0,
        "Gengar-Mega": 1.0,
        "Raichu": 1.0
      },
      "counters_json": {}
    },
    {
      "pokemon_name": "Azumarill",
      "usage_count": 4,
      "usage_pct": 9.52,
      "viability_json": [
        1,
        50,
        50,
        50
      ],
      "abilities_json": {
        "hugepower": 4.0
      },
      "items_json": {
        "sitrusberry": 4.0
      },
      "spreads_json": {
        "Adamant:8/248/0/0/0/252": 4.0
      },
      "moves_json": {
        "aquajet": 4.0,
        "playrough": 4.0,
        "doubleedge": 4.0,
        "bellydrum": 4.0
      },
      "tera_json": {
        "nothing": 4.0
      },
      "happiness_json": {
        "255": 4.0
      },
      "teammates_json": {
        "Aerodactyl": 4.0,
        "Garchomp": 4.0,
        "Gengar-Mega": 4.0,
        "Hydreigon": 4.0,
        "Tyranitar": 4.0
      },
      "counters_json": {}
    },
    {
      "pokemon_name": "Blastoise-Mega",
      "usage_count": 3,
      "usage_pct": 7.14,
      "viability_json": [
        1,
        34,
        34,
        34
      ],
      "abilities_json": {
        "megalauncher": 3.0
      },
      "items_json": {
        "blastoisinite": 3.0
      },
      "spreads_json": {
        "Quiet:244/4/4/252/4/0": 3.0
      },
      "moves_json": {
        "fakeout": 3.0,
        "waterspout": 3.0,
        "flashcannon": 3.0,
        "protect": 3.0
      },
      "tera_json": {
        "nothing": 3.0
      },
      "happiness_json": {
        "255": 3.0
      },
      "teammates_json": {
        "Gothitelle": 3.0,
        "Amoonguss": 3.0,
        "Mawile-Mega": 3.0,
        "Politoed": 3.0,
        "Escavalier": 3.0
      },
      "counters_json": {}
    },
    {
      "pokemon_name": "Chandelure",
      "usage_count": 6,
      "usage_pct": 14.29,
      "viability_json": [
        1,
        74,
        74,
        74
      ],
      "abilities_json": {
        "flashfire": 6.0
      },
      "items_json": {
        "colburberry": 6.0
      },
      "spreads_json": {
        "Modest:252/0/108/148/0/0": 6.0
      },
      "moves_json": {
        "flamethrower": 6.0,
        "trickroom": 6.0,
        "shadowball": 6.0,
        "protect": 6.0
      },
      "tera_json": {
        "nothing": 6.0
      },
      "happiness_json": {
        "255": 6.0
      },
      "teammates_json": {
        "Abomasnow-Mega": 6.0,
        "Conkeldurr": 6.0,
        "Aerodactyl": 6.0,
        "Garchomp": 6.0,
        "Greninja": 6.0
      },
      "counters_json": {}
    },
    {
      "pokemon_name": "Charizard-Mega-Y",
      "usage_count": 7,
      "usage_pct": 14.29,
      "viability_json": [
        1,
        63,
        63,
        63
      ],
      "abilities_json": {
        "drought": 7.0
      },
      "items_json": {
        "charizarditey": 7.0
      },
      "spreads_json": {
        "Modest:252/0/12/28/12/204": 7.0
      },
      "moves_json": {
        "heatwave": 7.0,
        "overheat": 7.0,
        "solarbeam": 7.0,
        "protect": 7.0
      },
      "tera_json": {
        "nothing": 7.0
      },
      "happiness_json": {
        "255": 7.0
      },
      "teammates_json": {
        "Tyranitar": 6.0,
        "Garchomp": 6.0,
        "Rotom-Wash": 6.0,
        "Mawile-Mega": 6.0,
        "Ludicolo": 6.0
      },
      "counters_json": {}
    },
    {
      "pokemon_name": "Clawitzer",
      "usage_count": 2,
      "usage_pct": 4.76,
      "viability_json": [
        1,
        43,
        43,
        43
      ],
      "abilities_json": {
        "megalauncher": 2.0
      },
      "items_json": {
        "assaultvest": 2.0
      },
      "spreads_json": {
        "Quiet:252/0/0/252/4/0": 2.0
      },
      "moves_json": {
        "darkpulse": 2.0,
        "dragonpulse": 2.0,
        "protect": 2.0,
        "aurasphere": 2.0
      },
      "tera_json": {
        "nothing": 2.0
      },
      "happiness_json": {
        "255": 2.0
      },
      "teammates_json": {
        "Mawile-Mega": 2.0,
        "Slowking": 2.0,
        "Amoonguss": 2.0,
        "Conkeldurr": 2.0,
        "Gothitelle": 2.0
      },
      "counters_json": {}
    },
    {
      "pokemon_name": "Conkeldurr",
      "usage_count": 9,
      "usage_pct": 21.43,
      "viability_json": [
        3,
        74,
        74,
        74
      ],
      "abilities_json": {
        "ironfist": 6.0,
        "guts": 3.0
      },
      "items_json": {
        "assaultvest": 7.0,
        "flameorb": 2.0
      },
      "spreads_json": {
        "Brave:100/156/0/0/252/0": 6.0,
        "Brave:252/252/0/0/4/0": 2.0,
        "Adamant:212/44/144/0/108/0": 1.0
      },
      "moves_json": {
        "drainpunch": 9.0,
        "machpunch": 7.0,
        "payback": 7.0,
        "rockslide": 9.0,
        "superpower": 2.0,
        "facade": 2.0
      },
      "tera_json": {
        "nothing": 9.0
      },
      "happiness_json": {
        "255": 9.0
      },
      "teammates_json": {
        "Abomasnow-Mega": 6.0,
        "Chandelure": 6.0,
        "Aerodactyl": 6.0,
        "Garchomp": 6.0,
        "Greninja": 6.0,
        "Mawile-Mega": 3.0,
        "Slowking": 2.0,
        "Amoonguss": 2.0,
        "Gothitelle": 2.0,
        "Clawitzer": 2.0,
        "Zapdos": 1.0,
        "Hydreigon": 1.0,
        "Tyranitar": 1.0,
        "Aegislash": 1.0
      },
      "counters_json": {}
    },
    {
      "pokemon_name": "Escavalier",
      "usage_count": 3,
      "usage_pct": 7.14,
      "viability_json": [
        1,
        34,
        34,
        34
      ],
      "abilities_json": {
        "overcoat": 3.0
      },
      "items_json": {
        "choiceband": 3.0
      },
      "spreads_json": {
        "Brave:252/252/0/0/4/0": 3.0
      },
      "moves_json": {
        "megahorn": 3.0,
        "ironhead": 3.0,
        "drillrun": 3.0,
        "knockoff": 3.0
      },
      "tera_json": {
        "nothing": 3.0
      },
      "happiness_json": {
        "255": 3.0
      },
      "teammates_json": {
        "Gothitelle": 3.0,
        "Amoonguss": 3.0,
        "Mawile-Mega": 3.0,
        "Blastoise-Mega": 3.0,
        "Politoed": 3.0
      },
      "counters_json": {}
    },
    {
      "pokemon_name": "Garchomp",
      "usage_count": 26,
      "usage_pct": 59.52,
      "viability_json": [
        8,
        74,
        74,
        63
      ],
      "abilities_json": {
        "roughskin": 26.0
      },
      "items_json": {
        "lifeorb": 10.0,
        "rockyhelmet": 4.0,
        "focussash": 3.0,
        "yacheberry": 6.0,
        "choiceband": 2.0,
        "lumberry": 1.0
      },
      "spreads_json": {
        "Jolly:0/252/4/0/0/252": 7.0,
        "Impish:236/0/180/0/0/92": 4.0,
        "Jolly:0/252/0/0/4/252": 12.0,
        "Jolly:12/204/4/0/36/252": 2.0,
        "Jolly:4/252/0/0/0/252": 1.0
      },
      "moves_json": {
        "dragonclaw": 22.0,
        "rockslide": 23.0,
        "earthquake": 26.0,
        "protect": 20.0,
        "poisonjab": 4.0,
        "dragontail": 4.0,
        "substitute": 3.0,
        "ironhead": 2.0
      },
      "tera_json": {
        "nothing": 26.0
      },
      "happiness_json": {
        "255": 26.0
      },
      "teammates_json": {
        "Charizard-Mega-Y": 6.0,
        "Tyranitar": 13.0,
        "Rotom-Wash": 11.0,
        "Mawile-Mega": 11.0,
        "Ludicolo": 6.0,
        "Aerodactyl": 10.0,
        "Azumarill": 4.0,
        "Gengar-Mega": 4.0,
        "Hydreigon": 4.0,
        "Talonflame": 7.0,
        "Zapdos": 3.0,
        "Amoonguss": 3.0,
        "Kangaskhan-Mega": 6.0,
        "Salamence": 4.0,
        "Aegislash": 2.0,
        "Abomasnow-Mega": 6.0,
        "Chandelure": 6.0,
        "Conkeldurr": 6.0,
        "Greninja": 6.0,
        "Smeargle": 2.0,
        "Alakazam-Mega": 2.0,
        "Gengar": 2.0,
        "Rotom-Heat": 1.0
      },
      "counters_json": {}
    },
    {
      "pokemon_name": "Garchomp-Mega",
      "usage_count": 2,
      "usage_pct": 4.76,
      "viability_json": [
        1,
        45,
        45,
        45
      ],
      "abilities_json": {
        "sandforce": 2.0
      },
      "items_json": {
        "garchompite": 2.0
      },
      "spreads_json": {
        "Jolly:28/124/4/0/100/252": 2.0
      },
      "moves_json": {
        "dragonclaw": 2.0,
        "earthquake": 2.0,
        "rockslide": 2.0,
        "protect": 2.0
      },
      "tera_json": {
        "nothing": 2.0
      },
      "happiness_json": {
        "255": 2.0
      },
      "teammates_json": {
        "Mawile-Mega": 2.0,
        "Rotom-Heat": 2.0,
        "Zapdos": 2.0,
        "Tyranitar": 2.0,
        "Aegislash": 2.0
      },
      "counters_json": {}
    },
    {
      "pokemon_name": "Gardevoir",
      "usage_count": 2,
      "usage_pct": 4.76,
      "viability_json": [
        1,
        38,
        38,
        38
      ],
      "abilities_json": {
        "synchronize": 2.0
      },
      "items_json": {
        "sitrusberry": 2.0
      },
      "spreads_json": {
        "Modest:252/0/116/132/4/4": 2.0
      },
      "moves_json": {
        "imprison": 2.0,
        "trickroom": 2.0,
        "dazzlinggleam": 2.0,
        "protect": 2.0
      },
      "tera_json": {
        "nothing": 2.0
      },
      "happiness_json": {
        "255": 2.0
      },
      "teammates_json": {
        "Kangaskhan-Mega": 2.0,
        "Smeargle": 2.0,
        "Talonflame": 2.0,
        "Haxorus": 2.0,
        "Alakazam-Mega": 2.0
      },
      "counters_json": {}
    },
    {
      "pokemon_name": "Gengar",
      "usage_count": 2,
      "usage_pct": 4.76,
      "viability_json": [
        2,
        61,
        61,
        61
      ],
      "abilities_json": {
        "levitate": 2.0
      },
      "items_json": {
        "focussash": 2.0
      },
      "spreads_json": {
        "Timid:4/0/0/252/0/252": 2.0
      },
      "moves_json": {
        "sludgebomb": 1.0,
        "shadowball": 2.0,
        "protect": 2.0,
        "willowisp": 2.0,
        "taunt": 1.0
      },
      "tera_json": {
        "nothing": 2.0
      },
      "happiness_json": {
        "255": 2.0
      },
      "teammates_json": {
        "Garchomp": 2.0,
        "Rotom-Wash": 1.0,
        "Kangaskhan-Mega": 2.0,
        "Mawile-Mega": 2.0,
        "Salamence": 2.0,
        "Rotom-Heat": 1.0
      },
      "counters_json": {}
    },
    {
      "pokemon_name": "Gengar-Mega",
      "usage_count": 5,
      "usage_pct": 11.9,
      "viability_json": [
        2,
        50,
        50,
        50
      ],
      "abilities_json": {
        "shadowtag": 5.0
      },
      "items_json": {
        "gengarite": 5.0
      },
      "spreads_json": {
        "Timid:252/0/4/0/0/252": 4.0,
        "Timid:252/0/52/4/20/180": 1.0
      },
      "moves_json": {
        "perishsong": 5.0,
        "substitute": 4.0,
        "protect": 5.0,
        "shadowball": 5.0,
        "disable": 1.0
      },
      "tera_json": {
        "nothing": 5.0
      },
      "happiness_json": {
        "255": 5.0
      },
      "teammates_json": {
        "Aerodactyl": 4.0,
        "Azumarill": 4.0,
        "Garchomp": 4.0,
        "Hydreigon": 4.0,
        "Tyranitar": 4.0,
        "Politoed": 1.0,
        "Scrafty": 1.0,
        "Amoonguss": 1.0,
        "Raichu": 1.0,
        "Gothitelle": 1.0
      },
      "counters_json": {}
    },
    {
      "pokemon_name": "Gigalith",
      "usage_count": 4,
      "usage_pct": 9.52,
      "viability_json": [
        1,
        48,
        48,
        48
      ],
      "abilities_json": {
        "sturdy": 4.0
      },
      "items_json": {
        "choiceband": 4.0
      },
      "spreads_json": {
        "Brave:252/252/0/0/4/0": 4.0
      },
      "moves_json": {
        "rockslide": 4.0,
        "earthquake": 4.0,
        "heavyslam": 4.0,
        "return": 4.0
      },
      "tera_json": {
        "nothing": 4.0
      },
      "happiness_json": {
        "255": 4.0
      },
      "teammates_json": {
        "Lucario-Mega": 4.0,
        "Scrafty": 4.0,
        "Aegislash": 4.0,
        "Amoonguss": 4.0,
        "Reuniclus": 4.0
      },
      "counters_json": {}
    },
    {
      "pokemon_name": "Gothitelle",
      "usage_count": 6,
      "usage_pct": 14.29,
      "viability_json": [
        3,
        43,
        43,
        43
      ],
      "abilities_json": {
        "shadowtag": 4.0,
        "competitive": 2.0
      },
      "items_json": {
        "mentalherb": 3.0,
        "sitrusberry": 3.0
      },
      "spreads_json": {
        "Sassy:252/0/100/0/156/0": 3.0,
        "Sassy:252/0/0/4/252/0": 2.0,
        "Bold:252/0/196/0/60/0": 1.0
      },
      "moves_json": {
        "psychic": 6.0,
        "safeguard": 3.0,
        "trickroom": 6.0,
        "protect": 6.0,
        "healpulse": 3.0
      },
      "tera_json": {
        "nothing": 6.0
      },
      "happiness_json": {
        "255": 6.0
      },
      "teammates_json": {
        "Amoonguss": 6.0,
        "Mawile-Mega": 5.0,
        "Blastoise-Mega": 3.0,
        "Politoed": 4.0,
        "Escavalier": 3.0,
        "Slowking": 2.0,
        "Conkeldurr": 2.0,
        "Clawitzer": 2.0,
        "Gengar-Mega": 1.0,
        "Scrafty": 1.0,
        "Raichu": 1.0
      },
      "counters_json": {}
    },
    {
      "pokemon_name": "Greninja",
      "usage_count": 9,
      "usage_pct": 19.05,
      "viability_json": [
        2,
        74,
        74,
        74
      ],
      "abilities_json": {
        "protean": 9.0
      },
      "items_json": {
        "lifeorb": 3.0,
        "choicescarf": 6.0
      },
      "spreads_json": {
        "Hardy:4/0/0/252/0/252": 3.0,
        "Modest:0/0/0/252/4/252": 6.0
      },
      "moves_json": {
        "icebeam": 3.0,
        "darkpulse": 9.0,
        "surf": 3.0,
        "protect": 3.0,
        "uturn": 6.0,
        "blizzard": 6.0,
        "scald": 6.0
      },
      "tera_json": {
        "nothing": 9.0
      },
      "happiness_json": {
        "255": 9.0
      },
      "teammates_json": {
        "Kangaskhan-Mega": 2.0,
        "Talonflame": 2.0,
        "Aegislash": 2.0,
        "Smeargle": 2.0,
        "Hydreigon": 2.0,
        "Abomasnow-Mega": 6.0,
        "Chandelure": 6.0,
        "Conkeldurr": 6.0,
        "Aerodactyl": 6.0,
        "Garchomp": 6.0
      },
      "counters_json": {}
    },
    {
      "pokemon_name": "Haxorus",
      "usage_count": 2,
      "usage_pct": 4.76,
      "viability_json": [
        1,
        38,
        38,
        38
      ],
      "abilities_json": {
        "rivalry": 2.0
      },
      "items_json": {
        "choicescarf": 2.0
      },
      "spreads_json": {
        "Adamant:0/252/0/0/4/252": 2.0
      },
      "moves_json": {
        "dragonclaw": 2.0,
        "earthquake": 2.0,
        "rockslide": 2.0,
        "poisonjab": 2.0
      },
      "tera_json": {
        "nothing": 2.0
      },
      "happiness_json": {
        "255": 2.0
      },
      "teammates_json": {
        "Kangaskhan-Mega": 2.0,
        "Smeargle": 2.0,
        "Talonflame": 2.0,
        "Gardevoir": 2.0,
        "Alakazam-Mega": 2.0
      },
      "counters_json": {}
    },
    {
      "pokemon_name": "Hydreigon",
      "usage_count": 8,
      "usage_pct": 16.67,
      "viability_json": [
        3,
        55,
        55,
        55
      ],
      "abilities_json": {
        "levitate": 8.0
      },
      "items_json": {
        "lifeorb": 4.0,
        "assaultvest": 3.0,
        "choicespecs": 1.0
      },
      "spreads_json": {
        "Timid:4/0/0/252/0/252": 4.0,
        "Modest:4/0/0/252/0/252": 3.0,
        "Modest:28/0/36/252/4/188": 1.0
      },
      "moves_json": {
        "dracometeor": 8.0,
        "darkpulse": 8.0,
        "fireblast": 5.0,
        "protect": 4.0,
        "earthpower": 4.0,
        "uturn": 3.0
      },
      "tera_json": {
        "nothing": 8.0
      },
      "happiness_json": {
        "255": 8.0
      },
      "teammates_json": {
        "Aerodactyl": 4.0,
        "Azumarill": 4.0,
        "Garchomp": 4.0,
        "Gengar-Mega": 4.0,
        "Tyranitar": 5.0,
        "Kangaskhan-Mega": 2.0,
        "Talonflame": 2.0,
        "Aegislash": 3.0,
        "Greninja": 2.0,
        "Smeargle": 2.0,
        "Mawile-Mega": 1.0,
        "Conkeldurr": 1.0,
        "Zapdos": 1.0
      },
      "counters_json": {}
    },
    {
      "pokemon_name": "Kangaskhan-Mega",
      "usage_count": 11,
      "usage_pct": 23.81,
      "viability_json": [
        5,
        61,
        61,
        61
      ],
      "abilities_json": {
        "parentalbond": 11.0
      },
      "items_json": {
        "kangaskhanite": 11.0
      },
      "spreads_json": {
        "Adamant:4/252/0/0/0/252": 3.0,
        "Jolly:0/252/0/0/4/252": 4.0,
        "Jolly:4/252/0/0/0/252": 2.0,
        "Adamant:212/132/4/0/100/60": 2.0
      },
      "moves_json": {
        "poweruppunch": 11.0,
        "suckerpunch": 7.0,
        "return": 7.0,
        "fakeout": 7.0,
        "crunch": 4.0,
        "protect": 8.0
      },
      "tera_json": {
        "nothing": 11.0
      },
      "happiness_json": {
        "255": 11.0
      },
      "teammates_json": {
        "Talonflame": 8.0,
        "Aegislash": 4.0,
        "Greninja": 2.0,
        "Smeargle": 6.0,
        "Hydreigon": 2.0,
        "Haxorus": 2.0,
        "Gardevoir": 2.0,
        "Alakazam-Mega": 4.0,
        "Rotom-Wash": 5.0,
        "Salamence": 4.0,
        "Garchomp": 6.0,
        "Mawile-Mega": 2.0,
        "Gengar": 2.0,
        "Rotom-Heat": 1.0
      },
      "counters_json": {}
    },
    {
      "pokemon_name": "Lucario-Mega",
      "usage_count": 4,
      "usage_pct": 9.52,
      "viability_json": [
        1,
        48,
        48,
        48
      ],
      "abilities_json": {
        "adaptability": 4.0
      },
      "items_json": {
        "lucarionite": 4.0
      },
      "spreads_json": {
        "Adamant:4/252/0/0/0/252": 4.0
      },
      "moves_json": {
        "protect": 4.0,
        "poweruppunch": 4.0,
        "closecombat": 4.0,
        "bulletpunch": 4.0
      },
      "tera_json": {
        "nothing": 4.0
      },
      "happiness_json": {
        "255": 4.0
      },
      "teammates_json": {
        "Scrafty": 4.0,
        "Aegislash": 4.0,
        "Amoonguss": 4.0,
        "Gigalith": 4.0,
        "Reuniclus": 4.0
      },
      "counters_json": {}
    },
    {
      "pokemon_name": "Ludicolo",
      "usage_count": 7,
      "usage_pct": 14.29,
      "viability_json": [
        1,
        63,
        63,
        63
      ],
      "abilities_json": {
        "swiftswim": 7.0
      },
      "items_json": {
        "assaultvest": 7.0
      },
      "spreads_json": {
        "Modest:252/0/84/148/4/20": 7.0
      },
      "moves_json": {
        "scald": 7.0,
        "gigadrain": 7.0,
        "icebeam": 7.0,
        "fakeout": 7.0
      },
      "tera_json": {
        "nothing": 7.0
      },
      "happiness_json": {
        "255": 7.0
      },
      "teammates_json": {
        "Charizard-Mega-Y": 6.0,
        "Tyranitar": 6.0,
        "Garchomp": 6.0,
        "Rotom-Wash": 6.0,
        "Mawile-Mega": 6.0
      },
      "counters_json": {}
    },
    {
      "pokemon_name": "Mawile-Mega",
      "usage_count": 20,
      "usage_pct": 45.24,
      "viability_json": [
        8,
        63,
        63,
        63
      ],
      "abilities_json": {
        "hugepower": 20.0
      },
      "items_json": {
        "mawilite": 20.0
      },
      "spreads_json": {
        "Adamant:252/212/4/0/4/36": 7.0,
        "Adamant:252/44/4/0/92/116": 3.0,
        "Careful:252/84/20/0/132/20": 2.0,
        "Adamant:252/252/0/0/4/0": 3.0,
        "Adamant:236/132/60/0/52/28": 2.0,
        "Brave:252/252/0/0/4/0": 2.0,
        "Adamant:252/116/4/0/116/20": 1.0
      },
      "moves_json": {
        "playrough": 17.0,
        "ironhead": 20.0,
        "suckerpunch": 18.0,
        "protect": 20.0,
        "swordsdance": 3.0,
        "crunch": 2.0
      },
      "tera_json": {
        "nothing": 20.0
      },
      "happiness_json": {
        "255": 20.0
      },
      "teammates_json": {
        "Charizard-Mega-Y": 6.0,
        "Tyranitar": 12.0,
        "Garchomp": 11.0,
        "Rotom-Wash": 7.0,
        "Ludicolo": 6.0,
        "Talonflame": 3.0,
        "Zapdos": 6.0,
        "Amoonguss": 8.0,
        "Garchomp-Mega": 2.0,
        "Rotom-Heat": 3.0,
        "Aegislash": 3.0,
        "Gothitelle": 5.0,
        "Blastoise-Mega": 3.0,
        "Politoed": 3.0,
        "Escavalier": 3.0,
        "Kangaskhan-Mega": 2.0,
        "Gengar": 2.0,
        "Salamence": 2.0,
        "Slowking": 2.0,
        "Conkeldurr": 3.0,
        "Clawitzer": 2.0,
        "Hydreigon": 1.0
      },
      "counters_json": {}
    },
    {
      "pokemon_name": "Politoed",
      "usage_count": 4,
      "usage_pct": 9.52,
      "viability_json": [
        2,
        36,
        36,
        36
      ],
      "abilities_json": {
        "drizzle": 4.0
      },
      "items_json": {
        "sitrusberry": 3.0,
        "leftovers": 1.0
      },
      "spreads_json": {
        "Sassy:252/0/252/0/4/0": 3.0,
        "Bold:252/0/164/4/84/4": 1.0
      },
      "moves_json": {
        "scald": 4.0,
        "perishsong": 4.0,
        "hypnosis": 3.0,
        "protect": 4.0,
        "icebeam": 1.0
      },
      "tera_json": {
        "nothing": 4.0
      },
      "happiness_json": {
        "255": 4.0
      },
      "teammates_json": {
        "Gothitelle": 4.0,
        "Amoonguss": 4.0,
        "Mawile-Mega": 3.0,
        "Blastoise-Mega": 3.0,
        "Escavalier": 3.0,
        "Gengar-Mega": 1.0,
        "Scrafty": 1.0,
        "Raichu": 1.0
      },
      "counters_json": {}
    },
    {
      "pokemon_name": "Raichu",
      "usage_count": 1,
      "usage_pct": 2.38,
      "viability_json": [
        1,
        36,
        36,
        36
      ],
      "abilities_json": {
        "lightningrod": 1.0
      },
      "items_json": {
        "focussash": 1.0
      },
      "spreads_json": {
        "Timid:84/0/164/4/4/252": 1.0
      },
      "moves_json": {
        "fakeout": 1.0,
        "encore": 1.0,
        "voltswitch": 1.0,
        "protect": 1.0
      },
      "tera_json": {
        "nothing": 1.0
      },
      "happiness_json": {
        "255": 1.0
      },
      "teammates_json": {
        "Gengar-Mega": 1.0,
        "Politoed": 1.0,
        "Scrafty": 1.0,
        "Amoonguss": 1.0,
        "Gothitelle": 1.0
      },
      "counters_json": {}
    },
    {
      "pokemon_name": "Reuniclus",
      "usage_count": 4,
      "usage_pct": 9.52,
      "viability_json": [
        1,
        48,
        48,
        48
      ],
      "abilities_json": {
        "magicguard": 4.0
      },
      "items_json": {
        "lifeorb": 4.0
      },
      "spreads_json": {
        "Quiet:252/0/4/252/0/0": 4.0
      },
      "moves_json": {
        "trickroom": 4.0,
        "focusblast": 1.0,
        "psychic": 4.0,
        "flashcannon": 4.0,
        "hiddenpowerice": 3.0
      },
      "tera_json": {
        "nothing": 4.0
      },
      "happiness_json": {
        "255": 4.0
      },
      "teammates_json": {
        "Lucario-Mega": 4.0,
        "Scrafty": 4.0,
        "Aegislash": 4.0,
        "Amoonguss": 4.0,
        "Gigalith": 4.0
      },
      "counters_json": {}
    },
    {
      "pokemon_name": "Rotom-Heat",
      "usage_count": 3,
      "usage_pct": 7.14,
      "viability_json": [
        2,
        54,
        54,
        54
      ],
      "abilities_json": {
        "levitate": 3.0
      },
      "items_json": {
        "sitrusberry": 3.0
      },
      "spreads_json": {
        "Calm:252/0/116/4/132/4": 2.0,
        "Modest:244/0/52/132/4/76": 1.0
      },
      "moves_json": {
        "thunderbolt": 3.0,
        "overheat": 3.0,
        "willowisp": 3.0,
        "protect": 3.0
      },
      "tera_json": {
        "nothing": 3.0
      },
      "happiness_json": {
        "255": 3.0
      },
      "teammates_json": {
        "Mawile-Mega": 3.0,
        "Garchomp-Mega": 2.0,
        "Zapdos": 2.0,
        "Tyranitar": 2.0,
        "Aegislash": 2.0,
        "Garchomp": 1.0,
        "Kangaskhan-Mega": 1.0,
        "Salamence": 1.0,
        "Gengar": 1.0
      },
      "counters_json": {}
    },
    {
      "pokemon_name": "Rotom-Wash",
      "usage_count": 12,
      "usage_pct": 26.19,
      "viability_json": [
        4,
        63,
        63,
        63
      ],
      "abilities_json": {
        "levitate": 12.0
      },
      "items_json": {
        "sitrusberry": 10.0,
        "choicescarf": 2.0
      },
      "spreads_json": {
        "Calm:252/0/44/76/132/4": 7.0,
        "Calm:244/0/52/76/132/4": 2.0,
        "Modest:4/0/0/252/0/252": 2.0,
        "Modest:220/0/4/116/4/164": 1.0
      },
      "moves_json": {
        "hydropump": 12.0,
        "thunderbolt": 10.0,
        "willowisp": 10.0,
        "protect": 10.0,
        "voltswitch": 2.0,
        "discharge": 2.0,
        "trick": 2.0
      },
      "tera_json": {
        "nothing": 12.0
      },
      "happiness_json": {
        "255": 12.0
      },
      "teammates_json": {
        "Charizard-Mega-Y": 6.0,
        "Tyranitar": 6.0,
        "Garchomp": 11.0,
        "Mawile-Mega": 7.0,
        "Ludicolo": 6.0,
        "Talonflame": 4.0,
        "Kangaskhan-Mega": 5.0,
        "Salamence": 3.0,
        "Aegislash": 2.0,
        "Smeargle": 2.0,
        "Alakazam-Mega": 2.0,
        "Gengar": 1.0
      },
      "counters_json": {}
    },
    {
      "pokemon_name": "Salamence",
      "usage_count": 4,
      "usage_pct": 9.52,
      "viability_json": [
        3,
        61,
        61,
        61
      ],
      "abilities_json": {
        "intimidate": 4.0
      },
      "items_json": {
        "choicescarf": 4.0
      },
      "spreads_json": {
        "Modest:36/0/68/236/4/164": 3.0,
        "Timid:4/0/0/252/0/252": 1.0
      },
      "moves_json": {
        "stoneedge": 4.0,
        "fireblast": 4.0,
        "dragonpulse": 4.0,
        "dracometeor": 4.0
      },
      "tera_json": {
        "nothing": 4.0
      },
      "happiness_json": {
        "255": 4.0
      },
      "teammates_json": {
        "Talonflame": 2.0,
        "Kangaskhan-Mega": 4.0,
        "Rotom-Wash": 3.0,
        "Aegislash": 2.0,
        "Garchomp": 4.0,
        "Mawile-Mega": 2.0,
        "Gengar": 2.0,
        "Rotom-Heat": 1.0
      },
      "counters_json": {}
    },
    {
      "pokemon_name": "Scrafty",
      "usage_count": 5,
      "usage_pct": 11.9,
      "viability_json": [
        2,
        48,
        48,
        48
      ],
      "abilities_json": {
        "intimidate": 5.0
      },
      "items_json": {
        "assaultvest": 4.0,
        "safetygoggles": 1.0
      },
      "spreads_json": {
        "Adamant:252/252/0/0/4/0": 4.0,
        "Careful:252/0/68/0/188/0": 1.0
      },
      "moves_json": {
        "fakeout": 5.0,
        "crunch": 4.0,
        "drainpunch": 5.0,
        "poweruppunch": 4.0,
        "quickguard": 1.0,
        "detect": 1.0
      },
      "tera_json": {
        "nothing": 5.0
      },
      "happiness_json": {
        "255": 5.0
      },
      "teammates_json": {
        "Lucario-Mega": 4.0,
        "Aegislash": 4.0,
        "Amoonguss": 5.0,
        "Gigalith": 4.0,
        "Reuniclus": 4.0,
        "Gengar-Mega": 1.0,
        "Politoed": 1.0,
        "Raichu": 1.0,
        "Gothitelle": 1.0
      },
      "counters_json": {}
    },
    {
      "pokemon_name": "Slowking",
      "usage_count": 2,
      "usage_pct": 4.76,
      "viability_json": [
        1,
        43,
        43,
        43
      ],
      "abilities_json": {
        "regenerator": 2.0
      },
      "items_json": {
        "leftovers": 2.0
      },
      "spreads_json": {
        "Relaxed:252/0/252/0/4/0": 2.0
      },
      "moves_json": {
        "trickroom": 2.0,
        "toxic": 2.0,
        "scald": 2.0,
        "lightscreen": 2.0
      },
      "tera_json": {
        "nothing": 2.0
      },
      "happiness_json": {
        "255": 2.0
      },
      "teammates_json": {
        "Mawile-Mega": 2.0,
        "Amoonguss": 2.0,
        "Conkeldurr": 2.0,
        "Gothitelle": 2.0,
        "Clawitzer": 2.0
      },
      "counters_json": {}
    },
    {
      "pokemon_name": "Smeargle",
      "usage_count": 7,
      "usage_pct": 14.29,
      "viability_json": [
        2,
        53,
        53,
        53
      ],
      "abilities_json": {
        "moody": 7.0
      },
      "items_json": {
        "focussash": 7.0
      },
      "spreads_json": {
        "Jolly:0/124/0/0/132/252": 3.0,
        "Jolly:0/0/148/0/108/252": 4.0
      },
      "moves_json": {
        "darkvoid": 7.0,
        "protect": 3.0,
        "icywind": 3.0,
        "fakeout": 3.0,
        "batonpass": 4.0,
        "destinybond": 1.0,
        "spikyshield": 4.0,
        "followme": 3.0
      },
      "tera_json": {
        "nothing": 7.0
      },
      "happiness_json": {
        "255": 7.0
      },
      "teammates_json": {
        "Kangaskhan-Mega": 6.0,
        "Talonflame": 6.0,
        "Aegislash": 2.0,
        "Greninja": 2.0,
        "Hydreigon": 2.0,
        "Haxorus": 2.0,
        "Gardevoir": 2.0,
        "Alakazam-Mega": 4.0,
        "Rotom-Wash": 2.0,
        "Garchomp": 2.0
      },
      "counters_json": {}
    },
    {
      "pokemon_name": "Talonflame",
      "usage_count": 12,
      "usage_pct": 26.19,
      "viability_json": [
        4,
        63,
        63,
        63
      ],
      "abilities_json": {
        "galewings": 12.0
      },
      "items_json": {
        "mentalherb": 3.0,
        "lifeorb": 7.0,
        "rockyhelmet": 2.0
      },
      "spreads_json": {
        "Adamant:252/252/0/0/0/4": 3.0,
        "Jolly:0/252/0/0/4/252": 4.0,
        "Naive:0/148/0/108/0/252": 3.0,
        "Jolly:252/44/76/0/4/132": 2.0
      },
      "moves_json": {
        "tailwind": 6.0,
        "bravebird": 12.0,
        "uturn": 3.0,
        "flareblitz": 9.0,
        "taunt": 6.0,
        "protect": 7.0,
        "overheat": 3.0,
        "willowisp": 2.0
      },
      "tera_json": {
        "nothing": 12.0
      },
      "happiness_json": {
        "255": 12.0
      },
      "teammates_json": {
        "Kangaskhan-Mega": 8.0,
        "Aegislash": 4.0,
        "Greninja": 2.0,
        "Smeargle": 6.0,
        "Hydreigon": 2.0,
        "Haxorus": 2.0,
        "Gardevoir": 2.0,
        "Alakazam-Mega": 4.0,
        "Mawile-Mega": 3.0,
        "Tyranitar": 3.0,
        "Garchomp": 7.0,
        "Zapdos": 3.0,
        "Amoonguss": 3.0,
        "Rotom-Wash": 4.0,
        "Salamence": 2.0
      },
      "counters_json": {}
    },
    {
      "pokemon_name": "Tyranitar",
      "usage_count": 17,
      "usage_pct": 38.1,
      "viability_json": [
        5,
        63,
        63,
        63
      ],
      "abilities_json": {
        "sandstream": 17.0
      },
      "items_json": {
        "choicescarf": 11.0,
        "lumberry": 4.0,
        "assaultvest": 2.0
      },
      "spreads_json": {
        "Timid:0/52/0/204/0/252": 8.0,
        "Jolly:4/252/0/0/0/252": 4.0,
        "Timid:0/44/4/204/4/252": 3.0,
        "Quiet:252/28/4/180/44/0": 2.0
      },
      "moves_json": {
        "rockslide": 17.0,
        "fireblast": 13.0,
        "icebeam": 13.0,
        "darkpulse": 11.0,
        "crunch": 4.0,
        "dragondance": 4.0,
        "earthquake": 4.0,
        "assurance": 2.0
      },
      "tera_json": {
        "nothing": 17.0
      },
      "happiness_json": {
        "255": 17.0
      },
      "teammates_json": {
        "Charizard-Mega-Y": 6.0,
        "Garchomp": 13.0,
        "Rotom-Wash": 6.0,
        "Mawile-Mega": 12.0,
        "Ludicolo": 6.0,
        "Aerodactyl": 4.0,
        "Azumarill": 4.0,
        "Gengar-Mega": 4.0,
        "Hydreigon": 5.0,
        "Talonflame": 3.0,
        "Zapdos": 6.0,
        "Amoonguss": 3.0,
        "Garchomp-Mega": 2.0,
        "Rotom-Heat": 2.0,
        "Aegislash": 3.0,
        "Conkeldurr": 1.0
      },
      "counters_json": {}
    },
    {
      "pokemon_name": "Zapdos",
      "usage_count": 6,
      "usage_pct": 14.29,
      "viability_json": [
        3,
        63,
        63,
        63
      ],
      "abilities_json": {
        "pressure": 6.0
      },
      "items_json": {
        "choicespecs": 3.0,
        "safetygoggles": 3.0
      },
      "spreads_json": {
        "Timid:0/0/8/244/4/252": 3.0,
        "Bold:252/0/132/4/108/12": 2.0,
        "Calm:220/0/144/28/76/36": 1.0
      },
      "moves_json": {
        "thunderbolt": 6.0,
        "hiddenpowerice": 4.0,
        "voltswitch": 3.0,
        "discharge": 3.0,
        "hiddenpowerdark": 2.0,
        "thunderwave": 3.0,
        "roost": 3.0
      },
      "tera_json": {
        "nothing": 6.0
      },
      "happiness_json": {
        "255": 6.0
      },
      "teammates_json": {
        "Mawile-Mega": 6.0,
        "Tyranitar": 6.0,
        "Garchomp": 3.0,
        "Talonflame": 3.0,
        "Amoonguss": 3.0,
        "Garchomp-Mega": 2.0,
        "Rotom-Heat": 2.0,
        "Aegislash": 3.0,
        "Conkeldurr": 1.0,
        "Hydreigon": 1.0
      },
      "counters_json": {}
    }
  ]
}