{
  "format_name": "gen9lc",
  "available_ratings": [
    0,
    1500,
    1630,
    1760
  ],
  "by_rating": {
    "0": {
      "elo_cutoff": 0,
      "pokemon": [
        {
          "pokemon_name": "Applin",
          "usage_count": 103,
          "usage_pct": 0.36
        },
        {
          "pokemon_name": "Arrokuda",
          "usage_count": 244,
          "usage_pct": 0.86
        },
        {
          "pokemon_name": "Axew",
          "usage_count": 955,
          "usage_pct": 3.47
        },
        {
          "pokemon_name": "Azurill",
          "usage_count": 595,
          "usage_pct": 2.15
        },
        {
          "pokemon_name": "Bagon",
          "usage_count": 385,
          "usage_pct": 1.38
        },
        {
          "pokemon_name": "Barboach",
          "usage_count": 197,
          "usage_pct": 0.68
        },
        {
          "pokemon_name": "Beldum",
          "usage_count": 114,
          "usage_pct": 0.4
        },
        {
          "pokemon_name": "Bellsprout",
          "usage_count": 428,
          "usage_pct": 1.32
        },
        {
          "pokemon_name": "Bergmite",
          "usage_count": 204,
          "usage_pct": 0.75
        },
        {
          "pokemon_name": "Blitzle",
          "usage_count": 274,
          "usage_pct": 1.0
        },
        {
          "pokemon_name": "Bonsly",
          "usage_count": 136,
          "usage_pct": 0.49
        },
        {
          "pokemon_name": "Bounsweet",
          "usage_count": 21,
          "usage_pct": 0.08
        },
        {
          "pokemon_name": "Bramblin",
          "usage_count": 622,
          "usage_pct": 2.3
        },
        {
          "pokemon_name": "Bronzor",
          "usage_count": 464,
          "usage_pct": 1.67
        },
        {
          "pokemon_name": "Buizel",
          "usage_count": 711,
          "usage_pct": 2.6
        },
        {
          "pokemon_name": "Bulbasaur",
          "usage_count": 655,
          "usage_pct": 2.36
        },
        {
          "pokemon_name": "Cacnea",
          "usage_count": 360,
          "usage_pct": 1.35
        },
        {
          "pokemon_name": "Capsakid",
          "usage_count": 24,
          "usage_pct": 0.09
        },
        {
          "pokemon_name": "Cetoddle",
          "usage_count": 401,
          "usage_pct": 1.46
        },
        {
          "pokemon_name": "Charcadet",
          "usage_count": 94,
          "usage_pct": 0.36
        },
        {
          "pokemon_name": "Charmander",
          "usage_count": 332,
          "usage_pct": 1.21
        },
        {
          "pokemon_name": "Chespin",
          "usage_count": 439,
          "usage_pct": 1.6
        },
        {
          "pokemon_name": "Chewtle",
          "usage_count": 143,
          "usage_pct": 0.51
        },
        {
          "pokemon_name": "Chikorita",
          "usage_count": 53,
          "usage_pct": 0.19
        },
        {
          "pokemon_name": "Chimchar",
          "usage_count": 225,
          "usage_pct": 0.82
        },
        {
          "pokemon_name": "Chinchou",
          "usage_count": 3266,
          "usage_pct": 11.89
        },
        {
          "pokemon_name": "Chingling",
          "usage_count": 120,
          "usage_pct": 0.44
        },
        {
          "pokemon_name": "Clauncher",
          "usage_count": 273,
          "usage_pct": 0.97
        },
        {
          "pokemon_name": "Cleffa",
          "usage_count": 147,
          "usage_pct": 0.52
        },
        {
          "pokemon_name": "Combee",
          "usage_count": 15,
          "usage_pct": 0.05
        },
        {
          "pokemon_name": "Corphish",
          "usage_count": 836,
          "usage_pct": 3.05
        },
        {
          "pokemon_name": "Cottonee",
          "usage_count": 600,
          "usage_pct": 2.21
        },
        {
          "pokemon_name": "Crabrawler",
          "usage_count": 408,
          "usage_pct": 1.51
        },
        {
          "pokemon_name": "Cranidos",
          "usage_count": 1027,
          "usage_pct": 3.7
        },
        {
          "pokemon_name": "Croagunk",
          "usage_count": 707,
          "usage_pct": 2.59
        },
        {
          "pokemon_name": "Cubchoo",
          "usage_count": 55,
          "usage_pct": 0.21
        },
        {
          "pokemon_name": "Cufant",
          "usage_count": 295,
          "usage_pct": 1.07
        },
        {
          "pokemon_name": "Cyndaquil",
          "usage_count": 335,
          "usage_pct": 1.23
        },
        {
          "pokemon_name": "Deerling",
          "usage_count": 424,
          "usage_pct": 1.58
        },
        {
          "pokemon_name": "Deino",
          "usage_count": 48,
          "usage_pct": 0.17
        },
        {
          "pokemon_name": "Dewpider",
          "usage_count": 456,
          "usage_pct": 1.69
        },
        {
          "pokemon_name": "Diglett-Alola",
          "usage_count": 3370,
          "usage_pct": 12.24
        },
        {
          "pokemon_name": "Doduo",
          "usage_count": 817,
          "usage_pct": 2.95
        },
        {
          "pokemon_name": "Dratini",
          "usage_count": 278,
          "usage_pct": 1.05
        },
        {
          "pokemon_name": "Dreepy",
          "usage_count": 185,
          "usage_pct": 0.65
        },
        {
          "pokemon_name": "Drifloon",
          "usage_count": 2471,
          "usage_pct": 8.98
        },
        {
          "pokemon_name": "Drilbur",
          "usage_count": 1391,
          "usage_pct": 4.95
        },
        {
          "pokemon_name": "Drowzee",
          "usage_count": 227,
          "usage_pct": 0.84
        },
        {
          "pokemon_name": "Ducklett",
          "usage_count": 72,
          "usage_pct": 0.27
        },
        {
          "pokemon_name": "Duskull",
          "usage_count": 456,
          "usage_pct": 1.65
        },
        {
          "pokemon_name": "Eevee",
          "usage_count": 281,
          "usage_pct": 1.0
        },
        {
          "pokemon_name": "Ekans",
          "usage_count": 479,
          "usage_pct": 1.62
        },
        {
          "pokemon_name": "Elekid",
          "usage_count": 6197,
          "usage_pct": 22.33
        },
        {
          "pokemon_name": "Espurr",
          "usage_count": 206,
          "usage_pct": 0.74
        },
        {
          "pokemon_name": "Exeggcute",
          "usage_count": 132,
          "usage_pct": 0.49
        },
        {
          "pokemon_name": "Feebas",
          "usage_count": 49,
          "usage_pct": 0.18
        },
        {
          "pokemon_name": "Fennekin",
          "usage_count": 160,
          "usage_pct": 0.58
        },
        {
          "pokemon_name": "Fidough",
          "usage_count": 76,
          "usage_pct": 0.28
        },
        {
          "pokemon_name": "Finizen",
          "usage_count": 77,
          "usage_pct": 0.28
        },
        {
          "pokemon_name": "Finneon",
          "usage_count": 62,
          "usage_pct": 0.22
        },
        {
          "pokemon_name": "Flabebe",
          "usage_count": 58,
          "usage_pct": 0.21
        },
        {
          "pokemon_name": "Fletchling",
          "usage_count": 262,
          "usage_pct": 0.92
        },
        {
          "pokemon_name": "Fomantis",
          "usage_count": 347,
          "usage_pct": 1.28
        },
        {
          "pokemon_name": "Foongus",
          "usage_count": 7433,
          "usage_pct": 26.77
        },
        {
          "pokemon_name": "Frigibax",
          "usage_count": 131,
          "usage_pct": 0.48
        },
        {
          "pokemon_name": "Froakie",
          "usage_count": 425,
          "usage_pct": 1.55
        },
        {
          "pokemon_name": "Fuecoco",
          "usage_count": 235,
          "usage_pct": 0.86
        },
        {
          "pokemon_name": "Geodude",
          "usage_count": 81,
          "usage_pct": 0.3
        },
        {
          "pokemon_name": "Geodude-Alola",
          "usage_count": 220,
          "usage_pct": 0.82
        },
        {
          "pokemon_name": "Gible",
          "usage_count": 516,
          "usage_pct": 1.91
        },
        {
          "pokemon_name": "Gimmighoul",
          "usage_count": 133,
          "usage_pct": 0.47
        },
        {
          "pokemon_name": "Gimmighoul-Roaming",
          "usage_count": 261,
          "usage_pct": 0.97
        },
        {
          "pokemon_name": "Glimmet",
          "usage_count": 6023,
          "usage_pct": 21.91
        },
        {
          "pokemon_name": "Golett",
          "usage_count": 242,
          "usage_pct": 0.88
        },
        {
          "pokemon_name": "Goomy",
          "usage_count": 137,
          "usage_pct": 0.49
        },
        {
          "pokemon_name": "Gothita",
          "usage_count": 1969,
          "usage_pct": 7.27
        },
        {
          "pokemon_name": "Greavard",
          "usage_count": 145,
          "usage_pct": 0.54
        },
        {
          "pokemon_name": "Grimer",
          "usage_count": 247,
          "usage_pct": 0.91
        },
        {
          "pokemon_name": "Grimer-Alola",
          "usage_count": 345,
          "usage_pct": 1.24
        },
        {
          "pokemon_name": "Grookey",
          "usage_count": 3566,
          "usage_pct": 12.98
        },
        {
          "pokemon_name": "Growlithe",
          "usage_count": 359,
          "usage_pct": 1.32
        },
        {
          "pokemon_name": "Growlithe-Hisui",
          "usage_count": 2135,
          "usage_pct": 7.77
        },
        {
          "pokemon_name": "Grubbin",
          "usage_count": 10,
          "usage_pct": 0.04
        },
        {
          "pokemon_name": "Gulpin",
          "usage_count": 51,
          "usage_pct": 0.18
        },
        {
          "pokemon_name": "Happiny",
          "usage_count": 67,
          "usage_pct": 0.23
        },
        {
          "pokemon_name": "Hatenna",
          "usage_count": 228,
          "usage_pct": 0.82
        },
        {
          "pokemon_name": "Hippopotas",
          "usage_count": 664,
          "usage_pct": 2.47
        },
        {
          "pokemon_name": "Hoothoot",
          "usage_count": 61,
          "usage_pct": 0.22
        },
        {
          "pokemon_name": "Hoppip",
          "usage_count": 20,
          "usage_pct": 0.07
        },
        {
          "pokemon_name": "Horsea",
          "usage_count": 219,
          "usage_pct": 0.81
        },
        {
          "pokemon_name": "Houndour",
          "usage_count": 628,
          "usage_pct": 2.27
        },
        {
          "pokemon_name": "Igglybuff",
          "usage_count": 42,
          "usage_pct": 0.16
        },
        {
          "pokemon_name": "Impidimp",
          "usage_count": 1841,
          "usage_pct": 6.81
        },
        {
          "pokemon_name": "Inkay",
          "usage_count": 252,
          "usage_pct": 0.91
        },
        {
          "pokemon_name": "Jangmo-o",
          "usage_count": 84,
          "usage_pct": 0.31
        },
        {
          "pokemon_name": "Joltik",
          "usage_count": 642,
          "usage_pct": 2.34
        },
        {
          "pokemon_name": "Koffing",
          "usage_count": 1574,
          "usage_pct": 5.8
        },
        {
          "pokemon_name": "Kricketot",
          "usage_count": 6,
          "usage_pct": 0.02
        },
        {
          "pokemon_name": "Larvesta",
          "usage_count": 1149,
          "usage_pct": 4.2
        },
        {
          "pokemon_name": "Larvitar",
          "usage_count": 260,
          "usage_pct": 0.94
        },
        {
          "pokemon_name": "Lechonk",
          "usage_count": 39,
          "usage_pct": 0.14
        },
        {
          "pokemon_name": "Litleo",
          "usage_count": 319,
          "usage_pct": 1.16
        },
        {
          "pokemon_name": "Litten",
          "usage_count": 446,
          "usage_pct": 1.64
        },
        {
          "pokemon_name": "Litwick",
          "usage_count": 105,
          "usage_pct": 0.39
        },
        {
          "pokemon_name": "Lotad",
          "usage_count": 59,
          "usage_pct": 0.21
        },
        {
          "pokemon_name": "Magikarp",
          "usage_count": 10,
          "usage_pct": 0.03
        },
        {
          "pokemon_name": "Magnemite",
          "usage_count": 981,
          "usage_pct": 3.62
        },
        {
          "pokemon_name": "Makuhita",
          "usage_count": 122,
          "usage_pct": 0.44
        },
        {
          "pokemon_name": "Mankey",
          "usage_count": 238,
          "usage_pct": 0.85
        },
        {
          "pokemon_name": "Mareanie",
          "usage_count": 3699,
          "usage_pct": 13.48
        },
        {
          "pokemon_name": "Mareep",
          "usage_count": 25,
          "usage_pct": 0.09
        },
        {
          "pokemon_name": "Maschiff",
          "usage_count": 127,
          "usage_pct": 0.47
        },
        {
          "pokemon_name": "Meowth",
          "usage_count": 1377,
          "usage_pct": 4.98
        },
        {
          "pokemon_name": "Meowth-Alola",
          "usage_count": 136,
          "usage_pct": 0.5
        },
        {
          "pokemon_name": "Meowth-Galar",
          "usage_count": 113,
          "usage_pct": 0.4
        },
        {
          "pokemon_name": "Mienfoo",
          "usage_count": 16993,
          "usage_pct": 61.46
        },
        {
          "pokemon_name": "Milcery",
          "usage_count": 17,
          "usage_pct": 0.07
        },
        {
          "pokemon_name": "Minccino",
          "usage_count": 1609,
          "usage_pct": 5.9
        },
        {
          "pokemon_name": "Mudbray",
          "usage_count": 8301,
          "usage_pct": 30.32
        },
        {
          "pokemon_name": "Mudkip",
          "usage_count": 26,
          "usage_pct": 0.09
        },
        {
          "pokemon_name": "Munchlax",
          "usage_count": 1239,
          "usage_pct": 4.56
        },
        {
          "pokemon_name": "Nacli",
          "usage_count": 50,
          "usage_pct": 0.18
        },
        {
          "pokemon_name": "Noibat",
          "usage_count": 99,
          "usage_pct": 0.36
        },
        {
          "pokemon_name": "Nosepass",
          "usage_count": 423,
          "usage_pct": 1.53
        },
        {
          "pokemon_name": "Numel",
          "usage_count": 1081,
          "usage_pct": 3.9
        },
        {
          "pokemon_name": "Nymble",
          "usage_count": 625,
          "usage_pct": 2.27
        },
        {
          "pokemon_name": "Oddish",
          "usage_count": 164,
          "usage_pct": 0.6
        },
        {
          "pokemon_name": "Oshawott",
          "usage_count": 60,
          "usage_pct": 0.21
        },
        {
          "pokemon_name": "Pawmi",
          "usage_count": 48,
          "usage_pct": 0.15
        },
        {
          "pokemon_name": "Pawniard",
          "usage_count": 2537,
          "usage_pct": 9.22
        },
        {
          "pokemon_name": "Petilil",
          "usage_count": 21,
          "usage_pct": 0.08
        },
        {
          "pokemon_name": "Phanpy",
          "usage_count": 114,
          "usage_pct": 0.43
        },
        {
          "pokemon_name": "Phantump",
          "usage_count": 335,
          "usage_pct": 1.18
        },
        {
          "pokemon_name": "Pichu",
          "usage_count": 131,
          "usage_pct": 0.46
        },
        {
          "pokemon_name": "Pikipek",
          "usage_count": 87,
          "usage_pct": 0.31
        },
        {
          "pokemon_name": "Pineco",
          "usage_count": 219,
          "usage_pct": 0.78
        },
        {
          "pokemon_name": "Piplup",
          "usage_count": 45,
          "usage_pct": 0.16
        },
        {
          "pokemon_name": "Poliwag",
          "usage_count": 344,
          "usage_pct": 1.26
        },
        {
          "pokemon_name": "Poltchageist",
          "usage_count": 138,
          "usage_pct": 0.51
        },
        {
          "pokemon_name": "Poochyena",
          "usage_count": 64,
          "usage_pct": 0.24
        },
        {
          "pokemon_name": "Popplio",
          "usage_count": 91,
          "usage_pct": 0.32
        },
        {
          "pokemon_name": "Psyduck",
          "usage_count": 171,
          "usage_pct": 0.63
        },
        {
          "pokemon_name": "Quaxly",
          "usage_count": 789,
          "usage_pct": 2.9
        },
        {
          "pokemon_name": "Ralts",
          "usage_count": 45,
          "usage_pct": 0.16
        },
        {
          "pokemon_name": "Rellor",
          "usage_count": 6,
          "usage_pct": 0.02
        },
        {
          "pokemon_name": "Rhyhorn",
          "usage_count": 116,
          "usage_pct": 0.41
        },
        {
          "pokemon_name": "Riolu",
          "usage_count": 650,
          "usage_pct": 2.36
        },
        {
          "pokemon_name": "Rockruff",
          "usage_count": 27,
          "usage_pct": 0.1
        },
        {
          "pokemon_name": "Rockruff-Dusk",
          "usage_count": 44,
          "usage_pct": 0.15
        },
        {
          "pokemon_name": "Rolycoly",
          "usage_count": 32,
          "usage_pct": 0.11
        },
        {
          "pokemon_name": "Rookidee",
          "usage_count": 13,
          "usage_pct": 0.05
        },
        {
          "pokemon_name": "Rowlet",
          "usage_count": 90,
          "usage_pct": 0.32
        },
        {
          "pokemon_name": "Salandit",
          "usage_count": 557,
          "usage_pct": 2.02
        },
        {
          "pokemon_name": "Sandile",
          "usage_count": 285,
          "usage_pct": 1.04
        },
        {
          "pokemon_name": "Sandshrew",
          "usage_count": 538,
          "usage_pct": 2.01
        },
        {
          "pokemon_name": "Sandshrew-Alola",
          "usage_count": 3013,
          "usage_pct": 11.05
        },
        {
          "pokemon_name": "Sandygast",
          "usage_count": 165,
          "usage_pct": 0.61
        },
        {
          "pokemon_name": "Scatterbug",
          "usage_count": 6,
          "usage_pct": 0.02
        },
        {
          "pokemon_name": "Scorbunny",
          "usage_count": 189,
          "usage_pct": 0.68
        },
        {
          "pokemon_name": "Seedot",
          "usage_count": 11,
          "usage_pct": 0.04
        },
        {
          "pokemon_name": "Seel",
          "usage_count": 110,
          "usage_pct": 0.4
        },
        {
          "pokemon_name": "Sentret",
          "usage_count": 21,
          "usage_pct": 0.07
        },
        {
          "pokemon_name": "Sewaddle",
          "usage_count": 42,
          "usage_pct": 0.15
        },
        {
          "pokemon_name": "Shellder",
          "usage_count": 5491,
          "usage_pct": 19.51
        },
        {
          "pokemon_name": "Shellos",
          "usage_count": 1014,
          "usage_pct": 3.76
        },
        {
          "pokemon_name": "Shieldon",
          "usage_count": 168,
          "usage_pct": 0.62
        },
        {
          "pokemon_name": "Shinx",
          "usage_count": 70,
          "usage_pct": 0.25
        },
        {
          "pokemon_name": "Shroodle",
          "usage_count": 1028,
          "usage_pct": 3.61
        },
        {
          "pokemon_name": "Shroomish",
          "usage_count": 254,
          "usage_pct": 0.94
        },
        {
          "pokemon_name": "Shuppet",
          "usage_count": 46,
          "usage_pct": 0.17
        },
        {
          "pokemon_name": "Silicobra",
          "usage_count": 145,
          "usage_pct": 0.51
        },
        {
          "pokemon_name": "Sinistea",
          "usage_count": 171,
          "usage_pct": 0.64
        },
        {
          "pokemon_name": "Skiddo",
          "usage_count": 187,
          "usage_pct": 0.69
        },
        {
          "pokemon_name": "Skrelp",
          "usage_count": 207,
          "usage_pct": 0.77
        },
        {
          "pokemon_name": "Skwovet",
          "usage_count": 43,
          "usage_pct": 0.16
        },
        {
          "pokemon_name": "Slakoth",
          "usage_count": 6,
          "usage_pct": 0.02
        },
        {
          "pokemon_name": "Slowpoke",
          "usage_count": 728,
          "usage_pct": 2.69
        },
        {
          "pokemon_name": "Slowpoke-Galar",
          "usage_count": 122,
          "usage_pct": 0.45
        },
        {
          "pokemon_name": "Slugma",
          "usage_count": 46,
          "usage_pct": 0.16
        },
        {
          "pokemon_name": "Smoliv",
          "usage_count": 67,
          "usage_pct": 0.23
        },
        {
          "pokemon_name": "Snom",
          "usage_count": 60,
          "usage_pct": 0.22
        },
        {
          "pokemon_name": "Snorunt",
          "usage_count": 30,
          "usage_pct": 0.1
        },
        {
          "pokemon_name": "Snover",
          "usage_count": 728,
          "usage_pct": 2.7
        },
        {
          "pokemon_name": "Snubbull",
          "usage_count": 371,
          "usage_pct": 1.38
        },
        {
          "pokemon_name": "Sobble",
          "usage_count": 57,
          "usage_pct": 0.21
        },
        {
          "pokemon_name": "Solosis",
          "usage_count": 682,
          "usage_pct": 2.47
        },
        {
          "pokemon_name": "Spinarak",
          "usage_count": 24,
          "usage_pct": 0.07
        },
        {
          "pokemon_name": "Spoink",
          "usage_count": 26,
          "usage_pct": 0.1
        },
        {
          "pokemon_name": "Sprigatito",
          "usage_count": 175,
          "usage_pct": 0.66
        },
        {
          "pokemon_name": "Squirtle",
          "usage_count": 469,
          "usage_pct": 1.73
        },
        {
          "pokemon_name": "Starly",
          "usage_count": 119,
          "usage_pct": 0.43
        },
        {
          "pokemon_name": "Stunky",
          "usage_count": 2916,
          "usage_pct": 10.64
        },
        {
          "pokemon_name": "Sunkern",
          "usage_count": 15,
          "usage_pct": 0.05
        },
        {
          "pokemon_name": "Surskit",
          "usage_count": 25,
          "usage_pct": 0.09
        },
        {
          "pokemon_name": "Swablu",
          "usage_count": 65,
          "usage_pct": 0.24
        },
        {
          "pokemon_name": "Swinub",
          "usage_count": 36,
          "usage_pct": 0.13
        },
        {
          "pokemon_name": "Tadbulb",
          "usage_count": 8,
          "usage_pct": 0.03
        },
        {
          "pokemon_name": "Tandemaus",
          "usage_count": 42,
          "usage_pct": 0.14
        },
        {
          "pokemon_name": "Tarountula",
          "usage_count": 9,
          "usage_pct": 0.03
        },
        {
          "pokemon_name": "Teddiursa",
          "usage_count": 291,
          "usage_pct": 1.07
        },
        {
          "pokemon_name": "Tentacool",
          "usage_count": 1122,
          "usage_pct": 4.08
        },
        {
          "pokemon_name": "Tepig",
          "usage_count": 51,
          "usage_pct": 0.18
        },
        {
          "pokemon_name": "Timburr",
          "usage_count": 670,
          "usage_pct": 2.42
        },
        {
          "pokemon_name": "Tinkatink",
          "usage_count": 3781,
          "usage_pct": 13.68
        },
        {
          "pokemon_name": "Toedscool",
          "usage_count": 4058,
          "usage_pct": 14.96
        },
        {
          "pokemon_name": "Totodile",
          "usage_count": 196,
          "usage_pct": 0.7
        },
        {
          "pokemon_name": "Toxel",
          "usage_count": 9,
          "usage_pct": 0.03
        },
        {
          "pokemon_name": "Trapinch",
          "usage_count": 1777,
          "usage_pct": 6.46
        },
        {
          "pokemon_name": "Treecko",
          "usage_count": 101,
          "usage_pct": 0.35
        },
        {
          "pokemon_name": "Turtwig",
          "usage_count": 148,
          "usage_pct": 0.54
        },
        {
          "pokemon_name": "Tynamo",
          "usage_count": 35,
          "usage_pct": 0.1
        },
        {
          "pokemon_name": "Tyrogue",
          "usage_count": 69,
          "usage_pct": 0.25
        },
        {
          "pokemon_name": "Varoom",
          "usage_count": 257,
          "usage_pct": 0.95
        },
        {
          "pokemon_name": "Venonat",
          "usage_count": 177,
          "usage_pct": 0.65
        },
        {
          "pokemon_name": "Voltorb",
          "usage_count": 554,
          "usage_pct": 2.01
        },
        {
          "pokemon_name": "Vullaby",
          "usage_count": 13884,
          "usage_pct": 50.24
        },
        {
          "pokemon_name": "Wattrel",
          "usage_count": 738,
          "usage_pct": 2.68
        },
        {
          "pokemon_name": "Wiglett",
          "usage_count": 86,
          "usage_pct": 0.31
        },
        {
          "pokemon_name": "Wingull",
          "usage_count": 1213,
          "usage_pct": 4.43
        },
        {
          "pokemon_name": "Wooper",
          "usage_count": 126,
          "usage_pct": 0.43
        },
        {
          "pokemon_name": "Wooper-Paldea",
          "usage_count": 158,
          "usage_pct": 0.59
        },
        {
          "pokemon_name": "Yungoos",
          "usage_count": 32,
          "usage_pct": 0.12
        },
        {
          "pokemon_name": "Zorua",
          "usage_count": 141,
          "usage_pct": 0.51
        },
        {
          "pokemon_name": "Zorua-Hisui",
          "usage_count": 2694,
          "usage_pct": 9.57
        }
      ]
    },
    "1500": {
      "elo_cutoff": 1500,
      "pokemon": [
        {
          "pokemon_name": "Applin",
          "usage_count": 26,
          "usage_pct": 0.13
        },
        {
          "pokemon_name": "Arrokuda",
          "usage_count": 70,
          "usage_pct": 0.34
        },
        {
          "pokemon_name": "Axew",
          "usage_count": 533,
          "usage_pct": 2.73
        },
        {
          "pokemon_name": "Azurill",
          "usage_count": 342,
          "usage_pct": 1.75
        },
        {
          "pokemon_name": "Bagon",
          "usage_count": 166,
          "usage_pct": 0.84
        },
        {
          "pokemon_name": "Barboach",
          "usage_count": 44,
          "usage_pct": 0.21
        },
        {
          "pokemon_name": "Beldum",
          "usage_count": 42,
          "usage_pct": 0.21
        },
        {
          "pokemon_name": "Bellsprout",
          "usage_count": 258,
          "usage_pct": 1.1
        },
        {
          "pokemon_name": "Bergmite",
          "usage_count": 68,
          "usage_pct": 0.35
        },
        {
          "pokemon_name": "Blitzle",
          "usage_count": 92,
          "usage_pct": 0.48
        },
        {
          "pokemon_name": "Bonsly",
          "usage_count": 53,
          "usage_pct": 0.26
        },
        {
          "pokemon_name": "Bounsweet",
          "usage_count": 5,
          "usage_pct": 0.03
        },
        {
          "pokemon_name": "Bramblin",
          "usage_count": 426,
          "usage_pct": 2.22
        },
        {
          "pokemon_name": "Bronzor",
          "usage_count": 192,
          "usage_pct": 0.98
        },
        {
          "pokemon_name": "Buizel",
          "usage_count": 441,
          "usage_pct": 2.29
        },
        {
          "pokemon_name": "Bulbasaur",
          "usage_count": 370,
          "usage_pct": 1.9
        },
        {
          "pokemon_name": "Cacnea",
          "usage_count": 184,
          "usage_pct": 0.96
        },
        {
          "pokemon_name": "Capsakid",
          "usage_count": 6,
          "usage_pct": 0.03
        },
        {
          "pokemon_name": "Cetoddle",
          "usage_count": 221,
          "usage_pct": 1.13
        },
        {
          "pokemon_name": "Charcadet",
          "usage_count": 31,
          "usage_pct": 0.17
        },
        {
          "pokemon_name": "Charmander",
          "usage_count": 122,
          "usage_pct": 0.61
        },
        {
          "pokemon_name": "Chespin",
          "usage_count": 328,
          "usage_pct": 1.66
        },
        {
          "pokemon_name": "Chewtle",
          "usage_count": 66,
          "usage_pct": 0.34
        },
        {
          "pokemon_name": "Chikorita",
          "usage_count": 14,
          "usage_pct": 0.07
        },
        {
          "pokemon_name": "Chimchar",
          "usage_count": 83,
          "usage_pct": 0.43
        },
        {
          "pokemon_name": "Chinchou",
          "usage_count": 2482,
          "usage_pct": 12.71
        },
        {
          "pokemon_name": "Chingling",
          "usage_count": 42,
          "usage_pct": 0.22
        },
        {
          "pokemon_name": "Clauncher",
          "usage_count": 98,
          "usage_pct": 0.49
        },
        {
          "pokemon_name": "Cleffa",
          "usage_count": 29,
          "usage_pct": 0.14
        },
        {
          "pokemon_name": "Combee",
          "usage_count": 6,
          "usage_pct": 0.03
        },
        {
          "pokemon_name": "Corphish",
          "usage_count": 538,
          "usage_pct": 2.77
        },
        {
          "pokemon_name": "Cottonee",
          "usage_count": 390,
          "usage_pct": 2.02
        },
        {
          "pokemon_name": "Crabrawler",
          "usage_count": 242,
          "usage_pct": 1.26
        },
        {
          "pokemon_name": "Cranidos",
          "usage_count": 455,
          "usage_pct": 2.32
        },
        {
          "pokemon_name": "Croagunk",
          "usage_count": 397,
          "usage_pct": 2.05
        },
        {
          "pokemon_name": "Cubchoo",
          "usage_count": 18,
          "usage_pct": 0.1
        },
        {
          "pokemon_name": "Cufant",
          "usage_count": 150,
          "usage_pct": 0.77
        },
        {
          "pokemon_name": "Cyndaquil",
          "usage_count": 215,
          "usage_pct": 1.12
        },
        {
          "pokemon_name": "Deerling",
          "usage_count": 201,
          "usage_pct": 1.05
        },
        {
          "pokemon_name": "Deino",
          "usage_count": 15,
          "usage_pct": 0.08
        },
        {
          "pokemon_name": "Dewpider",
          "usage_count": 271,
          "usage_pct": 1.41
        },
        {
          "pokemon_name": "Diglett-Alola",
          "usage_count": 2629,
          "usage_pct": 13.45
        },
        {
          "pokemon_name": "Doduo",
          "usage_count": 511,
          "usage_pct": 2.62
        },
        {
          "pokemon_name": "Dratini",
          "usage_count": 117,
          "usage_pct": 0.63
        },
        {
          "pokemon_name": "Dreepy",
          "usage_count": 76,
          "usage_pct": 0.37
        },
        {
          "pokemon_name": "Drifloon",
          "usage_count": 1598,
          "usage_pct": 8.2
        },
        {
          "pokemon_name": "Drilbur",
          "usage_count": 849,
          "usage_pct": 4.19
        },
        {
          "pokemon_name": "Drowzee",
          "usage_count": 63,
          "usage_pct": 0.32
        },
        {
          "pokemon_name": "Ducklett",
          "usage_count": 11,
          "usage_pct": 0.06
        },
        {
          "pokemon_name": "Duskull",
          "usage_count": 225,
          "usage_pct": 1.13
        },
        {
          "pokemon_name": "Eevee",
          "usage_count": 78,
          "usage_pct": 0.39
        },
        {
          "pokemon_name": "Ekans",
          "usage_count": 359,
          "usage_pct": 1.71
        },
        {
          "pokemon_name": "Elekid",
          "usage_count": 5088,
          "usage_pct": 25.87
        },
        {
          "pokemon_name": "Espurr",
          "usage_count": 65,
          "usage_pct": 0.33
        },
        {
          "pokemon_name": "Exeggcute",
          "usage_count": 41,
          "usage_pct": 0.21
        },
        {
          "pokemon_name": "Feebas",
          "usage_count": 29,
          "usage_pct": 0.15
        },
        {
          "pokemon_name": "Fennekin",
          "usage_count": 50,
          "usage_pct": 0.26
        },
        {
          "pokemon_name": "Fidough",
          "usage_count": 32,
          "usage_pct": 0.16
        },
        {
          "pokemon_name": "Finizen",
          "usage_count": 39,
          "usage_pct": 0.2
        },
        {
          "pokemon_name": "Finneon",
          "usage_count": 10,
          "usage_pct": 0.05
        },
        {
          "pokemon_name": "Flabebe",
          "usage_count": 29,
          "usage_pct": 0.15
        },
        {
          "pokemon_name": "Fletchling",
          "usage_count": 125,
          "usage_pct": 0.62
        },
        {
          "pokemon_name": "Fomantis",
          "usage_count": 149,
          "usage_pct": 0.79
        },
        {
          "pokemon_name": "Foongus",
          "usage_count": 5959,
          "usage_pct": 30.26
        },
        {
          "pokemon_name": "Frigibax",
          "usage_count": 38,
          "usage_pct": 0.19
        },
        {
          "pokemon_name": "Froakie",
          "usage_count": 269,
          "usage_pct": 1.38
        },
        {
          "pokemon_name": "Fuecoco",
          "usage_count": 101,
          "usage_pct": 0.52
        },
        {
          "pokemon_name": "Geodude",
          "usage_count": 33,
          "usage_pct": 0.17
        },
        {
          "pokemon_name": "Geodude-Alola",
          "usage_count": 113,
          "usage_pct": 0.59
        },
        {
          "pokemon_name": "Gible",
          "usage_count": 351,
          "usage_pct": 1.84
        },
        {
          "pokemon_name": "Gimmighoul",
          "usage_count": 66,
          "usage_pct": 0.33
        },
        {
          "pokemon_name": "Gimmighoul-Roaming",
          "usage_count": 172,
          "usage_pct": 0.91
        },
        {
          "pokemon_name": "Glimmet",
          "usage_count": 4300,
          "usage_pct": 22.11
        },
        {
          "pokemon_name": "Golett",
          "usage_count": 113,
          "usage_pct": 0.58
        },
        {
          "pokemon_name": "Goomy",
          "usage_count": 24,
          "usage_pct": 0.12
        },
        {
          "pokemon_name": "Gothita",
          "usage_count": 1610,
          "usage_pct": 8.34
        },
        {
          "pokemon_name": "Greavard",
          "usage_count": 98,
          "usage_pct": 0.52
        },
        {
          "pokemon_name": "Grimer",
          "usage_count": 157,
          "usage_pct": 0.81
        },
        {
          "pokemon_name": "Grimer-Alola",
          "usage_count": 223,
          "usage_pct": 1.12
        },
        {
          "pokemon_name": "Grookey",
          "usage_count": 2650,
          "usage_pct": 13.58
        },
        {
          "pokemon_name": "Growlithe",
          "usage_count": 125,
          "usage_pct": 0.65
        },
        {
          "pokemon_name": "Growlithe-Hisui",
          "usage_count": 1486,
          "usage_pct": 7.6
        },
        {
          "pokemon_name": "Grubbin",
          "usage_count": 2,
          "usage_pct": 0.01
        },
        {
          "pokemon_name": "Gulpin",
          "usage_count": 10,
          "usage_pct": 0.05
        },
        {
          "pokemon_name": "Happiny",
          "usage_count": 16,
          "usage_pct": 0.08
        },
        {
          "pokemon_name": "Hatenna",
          "usage_count": 104,
          "usage_pct": 0.53
        },
        {
          "pokemon_name": "Hippopotas",
          "usage_count": 409,
          "usage_pct": 2.14
        },
        {
          "pokemon_name": "Hoothoot",
          "usage_count": 8,
          "usage_pct": 0.04
        },
        {
          "pokemon_name": "Hoppip",
          "usage_count": 5,
          "usage_pct": 0.02
        },
        {
          "pokemon_name": "Horsea",
          "usage_count": 118,
          "usage_pct": 0.62
        },
        {
          "pokemon_name": "Houndour",
          "usage_count": 406,
          "usage_pct": 2.07
        },
        {
          "pokemon_name": "Igglybuff",
          "usage_count": 14,
          "usage_pct": 0.07
        },
        {
          "pokemon_name": "Impidimp",
          "usage_count": 1323,
          "usage_pct": 6.89
        },
        {
          "pokemon_name": "Inkay",
          "usage_count": 86,
          "usage_pct": 0.43
        },
        {
          "pokemon_name": "Jangmo-o",
          "usage_count": 50,
          "usage_pct": 0.27
        },
        {
          "pokemon_name": "Joltik",
          "usage_count": 482,
          "usage_pct": 2.47
        },
        {
          "pokemon_name": "Koffing",
          "usage_count": 1218,
          "usage_pct": 6.33
        },
        {
          "pokemon_name": "Larvesta",
          "usage_count": 920,
          "usage_pct": 4.72
        },
        {
          "pokemon_name": "Larvitar",
          "usage_count": 130,
          "usage_pct": 0.66
        },
        {
          "pokemon_name": "Lechonk",
          "usage_count": 11,
          "usage_pct": 0.06
        },
        {
          "pokemon_name": "Litleo",
          "usage_count": 179,
          "usage_pct": 0.93
        },
        {
          "pokemon_name": "Litten",
          "usage_count": 283,
          "usage_pct": 1.48
        },
        {
          "pokemon_name": "Litwick",
          "usage_count": 48,
          "usage_pct": 0.26
        },
        {
          "pokemon_name": "Lotad",
          "usage_count": 9,
          "usage_pct": 0.04
        },
        {
          "pokemon_name": "Magikarp",
          "usage_count": 4,
          "usage_pct": 0.02
        },
        {
          "pokemon_name": "Magnemite",
          "usage_count": 455,
          "usage_pct": 2.37
        },
        {
          "pokemon_name": "Makuhita",
          "usage_count": 66,
          "usage_pct": 0.32
        },
        {
          "pokemon_name": "Mankey",
          "usage_count": 90,
          "usage_pct": 0.44
        },
        {
          "pokemon_name": "Mareanie",
          "usage_count": 2915,
          "usage_pct": 14.98
        },
        {
          "pokemon_name": "Mareep",
          "usage_count": 9,
          "usage_pct": 0.04
        },
        {
          "pokemon_name": "Maschiff",
          "usage_count": 52,
          "usage_pct": 0.27
        },
        {
          "pokemon_name": "Meowth",
          "usage_count": 986,
          "usage_pct": 5.0
        },
        {
          "pokemon_name": "Meowth-Alola",
          "usage_count": 42,
          "usage_pct": 0.22
        },
        {
          "pokemon_name": "Meowth-Galar",
          "usage_count": 67,
          "usage_pct": 0.34
        },
        {
          "pokemon_name": "Mienfoo",
          "usage_count": 13506,
          "usage_pct": 68.83
        },
        {
          "pokemon_name": "Milcery",
          "usage_count": 2,
          "usage_pct": 0.01
        },
        {
          "pokemon_name": "Minccino",
          "usage_count": 1279,
          "usage_pct": 6.62
        },
        {
          "pokemon_name": "Mudbray",
          "usage_count": 6902,
          "usage_pct": 35.49
        },
        {
          "pokemon_name": "Mudkip",
          "usage_count": 6,
          "usage_pct": 0.03
        },
        {
          "pokemon_name": "Munchlax",
          "usage_count": 700,
          "usage_pct": 3.62
        },
        {
          "pokemon_name": "Nacli",
          "usage_count": 10,
          "usage_pct": 0.05
        },
        {
          "pokemon_name": "Noibat",
          "usage_count": 22,
          "usage_pct": 0.11
        },
        {
          "pokemon_name": "Nosepass",
          "usage_count": 193,
          "usage_pct": 0.96
        },
        {
          "pokemon_name": "Numel",
          "usage_count": 812,
          "usage_pct": 4.12
        },
        {
          "pokemon_name": "Nymble",
          "usage_count": 517,
          "usage_pct": 2.65
        },
        {
          "pokemon_name": "Oddish",
          "usage_count": 109,
          "usage_pct": 0.55
        },
        {
          "pokemon_name": "Oshawott",
          "usage_count": 19,
          "usage_pct": 0.09
        },
        {
          "pokemon_name": "Pawmi",
          "usage_count": 12,
          "usage_pct": 0.07
        },
        {
          "pokemon_name": "Pawniard",
          "usage_count": 1798,
          "usage_pct": 9.23
        },
        {
          "pokemon_name": "Petilil",
          "usage_count": 5,
          "usage_pct": 0.03
        },
        {
          "pokemon_name": "Phanpy",
          "usage_count": 39,
          "usage_pct": 0.21
        },
        {
          "pokemon_name": "Phantump",
          "usage_count": 269,
          "usage_pct": 1.33
        },
        {
          "pokemon_name": "Pichu",
          "usage_count": 28,
          "usage_pct": 0.14
        },
        {
          "pokemon_name": "Pikipek",
          "usage_count": 59,
          "usage_pct": 0.3
        },
        {
          "pokemon_name": "Pineco",
          "usage_count": 126,
          "usage_pct": 0.65
        },
        {
          "pokemon_name": "Piplup",
          "usage_count": 15,
          "usage_pct": 0.07
        },
        {
          "pokemon_name": "Poliwag",
          "usage_count": 251,
          "usage_pct": 1.29
        },
        {
          "pokemon_name": "Poltchageist",
          "usage_count": 60,
          "usage_pct": 0.31
        },
        {
          "pokemon_name": "Poochyena",
          "usage_count": 4,
          "usage_pct": 0.02
        },
        {
          "pokemon_name": "Popplio",
          "usage_count": 36,
          "usage_pct": 0.18
        },
        {
          "pokemon_name": "Psyduck",
          "usage_count": 84,
          "usage_pct": 0.43
        },
        {
          "pokemon_name": "Quaxly",
          "usage_count": 622,
          "usage_pct": 3.22
        },
        {
          "pokemon_name": "Ralts",
          "usage_count": 10,
          "usage_pct": 0.04
        },
        {
          "pokemon_name": "Rhyhorn",
          "usage_count": 47,
          "usage_pct": 0.23
        },
        {
          "pokemon_name": "Riolu",
          "usage_count": 389,
          "usage_pct": 1.97
        },
        {
          "pokemon_name": "Rockruff",
          "usage_count": 5,
          "usage_pct": 0.02
        },
        {
          "pokemon_name": "Rockruff-Dusk",
          "usage_count": 8,
          "usage_pct": 0.04
        },
        {
          "pokemon_name": "Rolycoly",
          "usage_count": 13,
          "usage_pct": 0.06
        },
        {
          "pokemon_name": "Rookidee",
          "usage_count": 3,
          "usage_pct": 0.02
        },
        {
          "pokemon_name": "Rowlet",
          "usage_count": 37,
          "usage_pct": 0.19
        },
        {
          "pokemon_name": "Salandit",
          "usage_count": 310,
          "usage_pct": 1.58
        },
        {
          "pokemon_name": "Sandile",
          "usage_count": 184,
          "usage_pct": 0.96
        },
        {
          "pokemon_name": "Sandshrew",
          "usage_count": 377,
          "usage_pct": 2.0
        },
        {
          "pokemon_name": "Sandshrew-Alola",
          "usage_count": 2409,
          "usage_pct": 12.42
        },
        {
          "pokemon_name": "Sandygast",
          "usage_count": 66,
          "usage_pct": 0.34
        },
        {
          "pokemon_name": "Scorbunny",
          "usage_count": 91,
          "usage_pct": 0.46
        },
        {
          "pokemon_name": "Seedot",
          "usage_count": 3,
          "usage_pct": 0.02
        },
        {
          "pokemon_name": "Seel",
          "usage_count": 59,
          "usage_pct": 0.3
        },
        {
          "pokemon_name": "Sentret",
          "usage_count": 6,
          "usage_pct": 0.03
        },
        {
          "pokemon_name": "Sewaddle",
          "usage_count": 5,
          "usage_pct": 0.03
        },
        {
          "pokemon_name": "Shellder",
          "usage_count": 4116,
          "usage_pct": 20.62
        },
        {
          "pokemon_name": "Shellos",
          "usage_count": 834,
          "usage_pct": 4.34
        },
        {
          "pokemon_name": "Shieldon",
          "usage_count": 61,
          "usage_pct": 0.31
        },
        {
          "pokemon_name": "Shinx",
          "usage_count": 18,
          "usage_pct": 0.09
        },
        {
          "pokemon_name": "Shroodle",
          "usage_count": 766,
          "usage_pct": 3.73
        },
        {
          "pokemon_name": "Shroomish",
          "usage_count": 69,
          "usage_pct": 0.35
        },
        {
          "pokemon_name": "Shuppet",
          "usage_count": 14,
          "usage_pct": 0.07
        },
        {
          "pokemon_name": "Silicobra",
          "usage_count": 83,
          "usage_pct": 0.42
        },
        {
          "pokemon_name": "Sinistea",
          "usage_count": 122,
          "usage_pct": 0.64
        },
        {
          "pokemon_name": "Skiddo",
          "usage_count": 106,
          "usage_pct": 0.55
        },
        {
          "pokemon_name": "Skrelp",
          "usage_count": 128,
          "usage_pct": 0.67
        },
        {
          "pokemon_name": "Skwovet",
          "usage_count": 10,
          "usage_pct": 0.05
        },
        {
          "pokemon_name": "Slowpoke",
          "usage_count": 434,
          "usage_pct": 2.24
        },
        {
          "pokemon_name": "Slowpoke-Galar",
          "usage_count": 57,
          "usage_pct": 0.29
        },
        {
          "pokemon_name": "Slugma",
          "usage_count": 15,
          "usage_pct": 0.07
        },
        {
          "pokemon_name": "Smoliv",
          "usage_count": 14,
          "usage_pct": 0.07
        },
        {
          "pokemon_name": "Snom",
          "usage_count": 34,
          "usage_pct": 0.18
        },
        {
          "pokemon_name": "Snorunt",
          "usage_count": 4,
          "usage_pct": 0.02
        },
        {
          "pokemon_name": "Snover",
          "usage_count": 480,
          "usage_pct": 2.52
        },
        {
          "pokemon_name": "Snubbull",
          "usage_count": 253,
          "usage_pct": 1.33
        },
        {
          "pokemon_name": "Sobble",
          "usage_count": 18,
          "usage_pct": 0.1
        },
        {
          "pokemon_name": "Solosis",
          "usage_count": 475,
          "usage_pct": 2.43
        },
        {
          "pokemon_name": "Spinarak",
          "usage_count": 12,
          "usage_pct": 0.06
        },
        {
          "pokemon_name": "Spoink",
          "usage_count": 12,
          "usage_pct": 0.06
        },
        {
          "pokemon_name": "Sprigatito",
          "usage_count": 58,
          "usage_pct": 0.31
        },
        {
          "pokemon_name": "Squirtle",
          "usage_count": 280,
          "usage_pct": 1.44
        },
        {
          "pokemon_name": "Starly",
          "usage_count": 75,
          "usage_pct": 0.37
        },
        {
          "pokemon_name": "Stunky",
          "usage_count": 2491,
          "usage_pct": 12.73
        },
        {
          "pokemon_name": "Sunkern",
          "usage_count": 5,
          "usage_pct": 0.02
        },
        {
          "pokemon_name": "Surskit",
          "usage_count": 10,
          "usage_pct": 0.05
        },
        {
          "pokemon_name": "Swablu",
          "usage_count": 16,
          "usage_pct": 0.08
        },
        {
          "pokemon_name": "Swinub",
          "usage_count": 16,
          "usage_pct": 0.08
        },
        {
          "pokemon_name": "Tadbulb",
          "usage_count": 3,
          "usage_pct": 0.02
        },
        {
          "pokemon_name": "Tandemaus",
          "usage_count": 18,
          "usage_pct": 0.09
        },
        {
          "pokemon_name": "Teddiursa",
          "usage_count": 203,
          "usage_pct": 1.06
        },
        {
          "pokemon_name": "Tentacool",
          "usage_count": 779,
          "usage_pct": 3.98
        },
        {
          "pokemon_name": "Tepig",
          "usage_count": 13,
          "usage_pct": 0.06
        },
        {
          "pokemon_name": "Timburr",
          "usage_count": 441,
          "usage_pct": 2.23
        },
        {
          "pokemon_name": "Tinkatink",
          "usage_count": 2977,
          "usage_pct": 15.16
        },
        {
          "pokemon_name": "Toedscool",
          "usage_count": 3383,
          "usage_pct": 17.56
        },
        {
          "pokemon_name": "Totodile",
          "usage_count": 46,
          "usage_pct": 0.23
        },
        {
          "pokemon_name": "Trapinch",
          "usage_count": 1391,
          "usage_pct": 7.12
        },
        {
          "pokemon_name": "Treecko",
          "usage_count": 27,
          "usage_pct": 0.13
        },
        {
          "pokemon_name": "Turtwig",
          "usage_count": 74,
          "usage_pct": 0.38
        },
        {
          "pokemon_name": "Tyrogue",
          "usage_count": 16,
          "usage_pct": 0.08
        },
        {
          "pokemon_name": "Varoom",
          "usage_count": 178,
          "usage_pct": 0.93
        },
        {
          "pokemon_name": "Venonat",
          "usage_count": 82,
          "usage_pct": 0.42
        },
        {
          "pokemon_name": "Voltorb",
          "usage_count": 217,
          "usage_pct": 1.12
        },
        {
          "pokemon_name": "Vullaby",
          "usage_count": 11172,
          "usage_pct": 56.91
        },
        {
          "pokemon_name": "Wattrel",
          "usage_count": 447,
          "usage_pct": 2.28
        },
        {
          "pokemon_name": "Wiglett",
          "usage_count": 19,
          "usage_pct": 0.1
        },
        {
          "pokemon_name": "Wingull",
          "usage_count": 875,
          "usage_pct": 4.51
        },
        {
          "pokemon_name": "Wooper",
          "usage_count": 66,
          "usage_pct": 0.32
        },
        {
          "pokemon_name": "Wooper-Paldea",
          "usage_count": 51,
          "usage_pct": 0.27
        },
        {
          "pokemon_name": "Yungoos",
          "usage_count": 18,
          "usage_pct": 0.09
        },
        {
          "pokemon_name": "Zorua",
          "usage_count": 84,
          "usage_pct": 0.43
        },
        {
          "pokemon_name": "Zorua-Hisui",
          "usage_count": 1781,
          "usage_pct": 8.85
        }
      ]
    },
    "1630": {
      "elo_cutoff": 1630,
      "pokemon": [
        {
          "pokemon_name": "Arrokuda",
          "usage_count": 3,
          "usage_pct": 0.03
        },
        {
          "pokemon_name": "Axew",
          "usage_count": 153,
          "usage_pct": 1.56
        },
        {
          "pokemon_name": "Azurill",
          "usage_count": 71,
          "usage_pct": 0.73
        },
        {
          "pokemon_name": "Bagon",
          "usage_count": 37,
          "usage_pct": 0.39
        },
        {
          "pokemon_name": "Barboach",
          "usage_count": 2,
          "usage_pct": 0.02
        },
        {
          "pokemon_name": "Bellsprout",
          "usage_count": 120,
          "usage_pct": 1.02
        },
        {
          "pokemon_name": "Bergmite",
          "usage_count": 13,
          "usage_pct": 0.14
        },
        {
          "pokemon_name": "Blitzle",
          "usage_count": 6,
          "usage_pct": 0.07
        },
        {
          "pokemon_name": "Bonsly",
          "usage_count": 2,
          "usage_pct": 0.02
        },
        {
          "pokemon_name": "Bramblin",
          "usage_count": 210,
          "usage_pct": 2.2
        },
        {
          "pokemon_name": "Bronzor",
          "usage_count": 24,
          "usage_pct": 0.24
        },
        {
          "pokemon_name": "Buizel",
          "usage_count": 228,
          "usage_pct": 2.34
        },
        {
          "pokemon_name": "Bulbasaur",
          "usage_count": 190,
          "usage_pct": 1.94
        },
        {
          "pokemon_name": "Cacnea",
          "usage_count": 46,
          "usage_pct": 0.48
        },
        {
          "pokemon_name": "Cetoddle",
          "usage_count": 44,
          "usage_pct": 0.44
        },
        {
          "pokemon_name": "Charcadet",
          "usage_count": 3,
          "usage_pct": 0.04
        },
        {
          "pokemon_name": "Charmander",
          "usage_count": 7,
          "usage_pct": 0.07
        },
        {
          "pokemon_name": "Chespin",
          "usage_count": 229,
          "usage_pct": 2.27
        },
        {
          "pokemon_name": "Chewtle",
          "usage_count": 10,
          "usage_pct": 0.09
        },
        {
          "pokemon_name": "Chimchar",
          "usage_count": 9,
          "usage_pct": 0.09
        },
        {
          "pokemon_name": "Chinchou",
          "usage_count": 1107,
          "usage_pct": 11.14
        },
        {
          "pokemon_name": "Chingling",
          "usage_count": 7,
          "usage_pct": 0.08
        },
        {
          "pokemon_name": "Clauncher",
          "usage_count": 7,
          "usage_pct": 0.07
        },
        {
          "pokemon_name": "Corphish",
          "usage_count": 266,
          "usage_pct": 2.7
        },
        {
          "pokemon_name": "Cottonee",
          "usage_count": 207,
          "usage_pct": 2.14
        },
        {
          "pokemon_name": "Crabrawler",
          "usage_count": 83,
          "usage_pct": 0.85
        },
        {
          "pokemon_name": "Cranidos",
          "usage_count": 91,
          "usage_pct": 0.94
        },
        {
          "pokemon_name": "Croagunk",
          "usage_count": 225,
          "usage_pct": 2.33
        },
        {
          "pokemon_name": "Cufant",
          "usage_count": 33,
          "usage_pct": 0.34
        },
        {
          "pokemon_name": "Cyndaquil",
          "usage_count": 99,
          "usage_pct": 1.03
        },
        {
          "pokemon_name": "Deerling",
          "usage_count": 43,
          "usage_pct": 0.45
        },
        {
          "pokemon_name": "Dewpider",
          "usage_count": 87,
          "usage_pct": 0.89
        },
        {
          "pokemon_name": "Diglett-Alola",
          "usage_count": 1276,
          "usage_pct": 12.8
        },
        {
          "pokemon_name": "Doduo",
          "usage_count": 260,
          "usage_pct": 2.62
        },
        {
          "pokemon_name": "Dratini",
          "usage_count": 18,
          "usage_pct": 0.19
        },
        {
          "pokemon_name": "Dreepy",
          "usage_count": 7,
          "usage_pct": 0.07
        },
        {
          "pokemon_name": "Drifloon",
          "usage_count": 909,
          "usage_pct": 9.17
        },
        {
          "pokemon_name": "Drilbur",
          "usage_count": 218,
          "usage_pct": 2.2
        },
        {
          "pokemon_name": "Drowzee",
          "usage_count": 17,
          "usage_pct": 0.18
        },
        {
          "pokemon_name": "Duskull",
          "usage_count": 35,
          "usage_pct": 0.34
        },
        {
          "pokemon_name": "Eevee",
          "usage_count": 9,
          "usage_pct": 0.1
        },
        {
          "pokemon_name": "Ekans",
          "usage_count": 201,
          "usage_pct": 1.89
        },
        {
          "pokemon_name": "Elekid",
          "usage_count": 2931,
          "usage_pct": 29.52
        },
        {
          "pokemon_name": "Espurr",
          "usage_count": 6,
          "usage_pct": 0.06
        },
        {
          "pokemon_name": "Exeggcute",
          "usage_count": 2,
          "usage_pct": 0.02
        },
        {
          "pokemon_name": "Feebas",
          "usage_count": 1,
          "usage_pct": 0.01
        },
        {
          "pokemon_name": "Fennekin",
          "usage_count": 3,
          "usage_pct": 0.03
        },
        {
          "pokemon_name": "Fidough",
          "usage_count": 8,
          "usage_pct": 0.08
        },
        {
          "pokemon_name": "Finizen",
          "usage_count": 7,
          "usage_pct": 0.07
        },
        {
          "pokemon_name": "Flabebe",
          "usage_count": 14,
          "usage_pct": 0.15
        },
        {
          "pokemon_name": "Fletchling",
          "usage_count": 37,
          "usage_pct": 0.37
        },
        {
          "pokemon_name": "Fomantis",
          "usage_count": 13,
          "usage_pct": 0.13
        },
        {
          "pokemon_name": "Foongus",
          "usage_count": 3207,
          "usage_pct": 32.23
        },
        {
          "pokemon_name": "Frigibax",
          "usage_count": 1,
          "usage_pct": 0.02
        },
        {
          "pokemon_name": "Froakie",
          "usage_count": 100,
          "usage_pct": 0.98
        },
        {
          "pokemon_name": "Fuecoco",
          "usage_count": 20,
          "usage_pct": 0.21
        },
        {
          "pokemon_name": "Geodude",
          "usage_count": 3,
          "usage_pct": 0.03
        },
        {
          "pokemon_name": "Geodude-Alola",
          "usage_count": 15,
          "usage_pct": 0.16
        },
        {
          "pokemon_name": "Gible",
          "usage_count": 128,
          "usage_pct": 1.35
        },
        {
          "pokemon_name": "Gimmighoul",
          "usage_count": 20,
          "usage_pct": 0.21
        },
        {
          "pokemon_name": "Gimmighoul-Roaming",
          "usage_count": 90,
          "usage_pct": 0.94
        },
        {
          "pokemon_name": "Glimmet",
          "usage_count": 2204,
          "usage_pct": 22.48
        },
        {
          "pokemon_name": "Golett",
          "usage_count": 5,
          "usage_pct": 0.05
        },
        {
          "pokemon_name": "Goomy",
          "usage_count": 1,
          "usage_pct": 0.01
        },
        {
          "pokemon_name": "Gothita",
          "usage_count": 934,
          "usage_pct": 9.52
        },
        {
          "pokemon_name": "Greavard",
          "usage_count": 59,
          "usage_pct": 0.63
        },
        {
          "pokemon_name": "Grimer",
          "usage_count": 77,
          "usage_pct": 0.8
        },
        {
          "pokemon_name": "Grimer-Alola",
          "usage_count": 63,
          "usage_pct": 0.65
        },
        {
          "pokemon_name": "Grookey",
          "usage_count": 1542,
          "usage_pct": 15.58
        },
        {
          "pokemon_name": "Growlithe",
          "usage_count": 20,
          "usage_pct": 0.21
        },
        {
          "pokemon_name": "Growlithe-Hisui",
          "usage_count": 758,
          "usage_pct": 7.69
        },
        {
          "pokemon_name": "Hatenna",
          "usage_count": 7,
          "usage_pct": 0.07
        },
        {
          "pokemon_name": "Hippopotas",
          "usage_count": 109,
          "usage_pct": 1.13
        },
        {
          "pokemon_name": "Horsea",
          "usage_count": 43,
          "usage_pct": 0.45
        },
        {
          "pokemon_name": "Houndour",
          "usage_count": 246,
          "usage_pct": 2.46
        },
        {
          "pokemon_name": "Igglybuff",
          "usage_count": 5,
          "usage_pct": 0.05
        },
        {
          "pokemon_name": "Impidimp",
          "usage_count": 691,
          "usage_pct": 7.09
        },
        {
          "pokemon_name": "Inkay",
          "usage_count": 5,
          "usage_pct": 0.04
        },
        {
          "pokemon_name": "Jangmo-o",
          "usage_count": 19,
          "usage_pct": 0.21
        },
        {
          "pokemon_name": "Joltik",
          "usage_count": 368,
          "usage_pct": 3.73
        },
        {
          "pokemon_name": "Koffing",
          "usage_count": 638,
          "usage_pct": 6.55
        },
        {
          "pokemon_name": "Larvesta",
          "usage_count": 493,
          "usage_pct": 4.99
        },
        {
          "pokemon_name": "Larvitar",
          "usage_count": 21,
          "usage_pct": 0.21
        },
        {
          "pokemon_name": "Litleo",
          "usage_count": 72,
          "usage_pct": 0.73
        },
        {
          "pokemon_name": "Litten",
          "usage_count": 76,
          "usage_pct": 0.77
        },
        {
          "pokemon_name": "Litwick",
          "usage_count": 8,
          "usage_pct": 0.08
        },
        {
          "pokemon_name": "Magnemite",
          "usage_count": 139,
          "usage_pct": 1.43
        },
        {
          "pokemon_name": "Makuhita",
          "usage_count": 7,
          "usage_pct": 0.06
        },
        {
          "pokemon_name": "Mankey",
          "usage_count": 7,
          "usage_pct": 0.06
        },
        {
          "pokemon_name": "Mareanie",
          "usage_count": 1517,
          "usage_pct": 15.51
        },
        {
          "pokemon_name": "Maschiff",
          "usage_count": 8,
          "usage_pct": 0.08
        },
        {
          "pokemon_name": "Meowth",
          "usage_count": 441,
          "usage_pct": 4.36
        },
        {
          "pokemon_name": "Meowth-Alola",
          "usage_count": 12,
          "usage_pct": 0.12
        },
        {
          "pokemon_name": "Meowth-Galar",
          "usage_count": 12,
          "usage_pct": 0.13
        },
        {
          "pokemon_name": "Mienfoo",
          "usage_count": 7372,
          "usage_pct": 74.61
        },
        {
          "pokemon_name": "Minccino",
          "usage_count": 799,
          "usage_pct": 8.2
        },
        {
          "pokemon_name": "Mudbray",
          "usage_count": 4160,
          "usage_pct": 42.43
        },
        {
          "pokemon_name": "Munchlax",
          "usage_count": 229,
          "usage_pct": 2.33
        },
        {
          "pokemon_name": "Noibat",
          "usage_count": 2,
          "usage_pct": 0.02
        },
        {
          "pokemon_name": "Nosepass",
          "usage_count": 25,
          "usage_pct": 0.25
        },
        {
          "pokemon_name": "Numel",
          "usage_count": 444,
          "usage_pct": 4.48
        },
        {
          "pokemon_name": "Nymble",
          "usage_count": 317,
          "usage_pct": 3.19
        },
        {
          "pokemon_name": "Oddish",
          "usage_count": 27,
          "usage_pct": 0.27
        },
        {
          "pokemon_name": "Oshawott",
          "usage_count": 1,
          "usage_pct": 0.01
        },
        {
          "pokemon_name": "Pawniard",
          "usage_count": 928,
          "usage_pct": 9.39
        },
        {
          "pokemon_name": "Phanpy",
          "usage_count": 11,
          "usage_pct": 0.11
        },
        {
          "pokemon_name": "Phantump",
          "usage_count": 138,
          "usage_pct": 1.3
        },
        {
          "pokemon_name": "Pichu",
          "usage_count": 2,
          "usage_pct": 0.01
        },
        {
          "pokemon_name": "Pikipek",
          "usage_count": 29,
          "usage_pct": 0.3
        },
        {
          "pokemon_name": "Pineco",
          "usage_count": 21,
          "usage_pct": 0.22
        },
        {
          "pokemon_name": "Poliwag",
          "usage_count": 176,
          "usage_pct": 1.76
        },
        {
          "pokemon_name": "Poltchageist",
          "usage_count": 7,
          "usage_pct": 0.07
        },
        {
          "pokemon_name": "Popplio",
          "usage_count": 7,
          "usage_pct": 0.08
        },
        {
          "pokemon_name": "Psyduck",
          "usage_count": 12,
          "usage_pct": 0.12
        },
        {
          "pokemon_name": "Quaxly",
          "usage_count": 393,
          "usage_pct": 4.03
        },
        {
          "pokemon_name": "Rhyhorn",
          "usage_count": 11,
          "usage_pct": 0.11
        },
        {
          "pokemon_name": "Riolu",
          "usage_count": 115,
          "usage_pct": 1.13
        },
        {
          "pokemon_name": "Rowlet",
          "usage_count": 15,
          "usage_pct": 0.15
        },
        {
          "pokemon_name": "Salandit",
          "usage_count": 107,
          "usage_pct": 1.09
        },
        {
          "pokemon_name": "Sandile",
          "usage_count": 117,
          "usage_pct": 1.21
        },
        {
          "pokemon_name": "Sandshrew",
          "usage_count": 139,
          "usage_pct": 1.45
        },
        {
          "pokemon_name": "Sandshrew-Alola",
          "usage_count": 1319,
          "usage_pct": 13.44
        },
        {
          "pokemon_name": "Sandygast",
          "usage_count": 15,
          "usage_pct": 0.16
        },
        {
          "pokemon_name": "Scorbunny",
          "usage_count": 40,
          "usage_pct": 0.4
        },
        {
          "pokemon_name": "Seel",
          "usage_count": 3,
          "usage_pct": 0.03
        },
        {
          "pokemon_name": "Shellder",
          "usage_count": 1991,
          "usage_pct": 20.04
        },
        {
          "pokemon_name": "Shellos",
          "usage_count": 550,
          "usage_pct": 5.6
        },
        {
          "pokemon_name": "Shieldon",
          "usage_count": 9,
          "usage_pct": 0.08
        },
        {
          "pokemon_name": "Shroodle",
          "usage_count": 224,
          "usage_pct": 2.26
        },
        {
          "pokemon_name": "Shroomish",
          "usage_count": 17,
          "usage_pct": 0.18
        },
        {
          "pokemon_name": "Shuppet",
          "usage_count": 1,
          "usage_pct": 0.01
        },
        {
          "pokemon_name": "Silicobra",
          "usage_count": 33,
          "usage_pct": 0.34
        },
        {
          "pokemon_name": "Sinistea",
          "usage_count": 73,
          "usage_pct": 0.77
        },
        {
          "pokemon_name": "Skiddo",
          "usage_count": 36,
          "usage_pct": 0.37
        },
        {
          "pokemon_name": "Skrelp",
          "usage_count": 23,
          "usage_pct": 0.25
        },
        {
          "pokemon_name": "Slowpoke",
          "usage_count": 229,
          "usage_pct": 2.32
        },
        {
          "pokemon_name": "Slowpoke-Galar",
          "usage_count": 10,
          "usage_pct": 0.1
        },
        {
          "pokemon_name": "Slugma",
          "usage_count": 2,
          "usage_pct": 0.03
        },
        {
          "pokemon_name": "Smoliv",
          "usage_count": 1,
          "usage_pct": 0.01
        },
        {
          "pokemon_name": "Snom",
          "usage_count": 19,
          "usage_pct": 0.19
        },
        {
          "pokemon_name": "Snover",
          "usage_count": 227,
          "usage_pct": 2.36
        },
        {
          "pokemon_name": "Snubbull",
          "usage_count": 107,
          "usage_pct": 1.12
        },
        {
          "pokemon_name": "Sobble",
          "usage_count": 1,
          "usage_pct": 0.01
        },
        {
          "pokemon_name": "Solosis",
          "usage_count": 227,
          "usage_pct": 2.31
        },
        {
          "pokemon_name": "Spinarak",
          "usage_count": 1,
          "usage_pct": 0.01
        },
        {
          "pokemon_name": "Spoink",
          "usage_count": 2,
          "usage_pct": 0.02
        },
        {
          "pokemon_name": "Sprigatito",
          "usage_count": 2,
          "usage_pct": 0.02
        },
        {
          "pokemon_name": "Squirtle",
          "usage_count": 98,
          "usage_pct": 0.99
        },
        {
          "pokemon_name": "Starly",
          "usage_count": 8,
          "usage_pct": 0.08
        },
        {
          "pokemon_name": "Stunky",
          "usage_count": 1650,
          "usage_pct": 16.61
        },
        {
          "pokemon_name": "Swinub",
          "usage_count": 2,
          "usage_pct": 0.02
        },
        {
          "pokemon_name": "Tandemaus",
          "usage_count": 1,
          "usage_pct": 0.01
        },
        {
          "pokemon_name": "Teddiursa",
          "usage_count": 42,
          "usage_pct": 0.43
        },
        {
          "pokemon_name": "Tentacool",
          "usage_count": 379,
          "usage_pct": 3.79
        },
        {
          "pokemon_name": "Timburr",
          "usage_count": 148,
          "usage_pct": 1.47
        },
        {
          "pokemon_name": "Tinkatink",
          "usage_count": 1803,
          "usage_pct": 18.14
        },
        {
          "pokemon_name": "Toedscool",
          "usage_count": 2047,
          "usage_pct": 20.99
        },
        {
          "pokemon_name": "Totodile",
          "usage_count": 4,
          "usage_pct": 0.04
        },
        {
          "pokemon_name": "Trapinch",
          "usage_count": 703,
          "usage_pct": 7.12
        },
        {
          "pokemon_name": "Treecko",
          "usage_count": 1,
          "usage_pct": 0.02
        },
        {
          "pokemon_name": "Turtwig",
          "usage_count": 20,
          "usage_pct": 0.21
        },
        {
          "pokemon_name": "Tyrogue",
          "usage_count": 2,
          "usage_pct": 0.02
        },
        {
          "pokemon_name": "Varoom",
          "usage_count": 161,
          "usage_pct": 1.66
        },
        {
          "pokemon_name": "Venonat",
          "usage_count": 39,
          "usage_pct": 0.39
        },
        {
          "pokemon_name": "Voltorb",
          "usage_count": 30,
          "usage_pct": 0.29
        },
        {
          "pokemon_name": "Vullaby",
          "usage_count": 5962,
          "usage_pct": 60.5
        },
        {
          "pokemon_name": "Wattrel",
          "usage_count": 220,
          "usage_pct": 2.19
        },
        {
          "pokemon_name": "Wiglett",
          "usage_count": 4,
          "usage_pct": 0.04
        },
        {
          "pokemon_name": "Wingull",
          "usage_count": 431,
          "usage_pct": 4.42
        },
        {
          "pokemon_name": "Wooper",
          "usage_count": 12,
          "usage_pct": 0.11
        },
        {
          "pokemon_name": "Wooper-Paldea",
          "usage_count": 2,
          "usage_pct": 0.02
        },
        {
          "pokemon_name": "Yungoos",
          "usage_count": 8,
          "usage_pct": 0.07
        },
        {
          "pokemon_name": "Zorua",
          "usage_count": 41,
          "usage_pct": 0.43
        },
        {
          "pokemon_name": "Zorua-Hisui",
          "usage_count": 776,
          "usage_pct": 7.76
        }
      ]
    },
    "1760": {
      "elo_cutoff": 1760,
      "pokemon": [
        {
          "pokemon_name": "Axew",
          "usage_count": 31,
          "usage_pct": 1.18
        },
        {
          "pokemon_name": "Azurill",
          "usage_count": 3,
          "usage_pct": 0.12
        },
        {
          "pokemon_name": "Bagon",
          "usage_count": 2,
          "usage_pct": 0.09
        },
        {
          "pokemon_name": "Blitzle",
          "usage_count": 0,
          "usage_pct": 0.01
        },
        {
          "pokemon_name": "Bramblin",
          "usage_count": 51,
          "usage_pct": 2.0
        },
        {
          "pokemon_name": "Buizel",
          "usage_count": 50,
          "usage_pct": 1.9
        },
        {
          "pokemon_name": "Bulbasaur",
          "usage_count": 2,
          "usage_pct": 0.06
        },
        {
          "pokemon_name": "Cetoddle",
          "usage_count": 1,
          "usage_pct": 0.05
        },
        {
          "pokemon_name": "Chespin",
          "usage_count": 32,
          "usage_pct": 1.22
        },
        {
          "pokemon_name": "Chimchar",
          "usage_count": 0,
          "usage_pct": 0.01
        },
        {
          "pokemon_name": "Chinchou",
          "usage_count": 273,
          "usage_pct": 10.31
        },
        {
          "pokemon_name": "Chingling",
          "usage_count": 1,
          "usage_pct": 0.05
        },
        {
          "pokemon_name": "Clauncher",
          "usage_count": 1,
          "usage_pct": 0.05
        },
        {
          "pokemon_name": "Corphish",
          "usage_count": 31,
          "usage_pct": 1.14
        },
        {
          "pokemon_name": "Cottonee",
          "usage_count": 36,
          "usage_pct": 1.38
        },
        {
          "pokemon_name": "Crabrawler",
          "usage_count": 6,
          "usage_pct": 0.23
        },
        {
          "pokemon_name": "Cranidos",
          "usage_count": 9,
          "usage_pct": 0.36
        },
        {
          "pokemon_name": "Croagunk",
          "usage_count": 17,
          "usage_pct": 0.66
        },
        {
          "pokemon_name": "Cufant",
          "usage_count": 8,
          "usage_pct": 0.29
        },
        {
          "pokemon_name": "Cyndaquil",
          "usage_count": 36,
          "usage_pct": 1.38
        },
        {
          "pokemon_name": "Deerling",
          "usage_count": 21,
          "usage_pct": 0.82
        },
        {
          "pokemon_name": "Dewpider",
          "usage_count": 13,
          "usage_pct": 0.5
        },
        {
          "pokemon_name": "Diglett-Alola",
          "usage_count": 293,
          "usage_pct": 10.94
        },
        {
          "pokemon_name": "Doduo",
          "usage_count": 66,
          "usage_pct": 2.4
        },
        {
          "pokemon_name": "Dratini",
          "usage_count": 3,
          "usage_pct": 0.11
        },
        {
          "pokemon_name": "Drifloon",
          "usage_count": 232,
          "usage_pct": 8.69
        },
        {
          "pokemon_name": "Drilbur",
          "usage_count": 41,
          "usage_pct": 1.54
        },
        {
          "pokemon_name": "Drowzee",
          "usage_count": 2,
          "usage_pct": 0.09
        },
        {
          "pokemon_name": "Duskull",
          "usage_count": 3,
          "usage_pct": 0.11
        },
        {
          "pokemon_name": "Eevee",
          "usage_count": 7,
          "usage_pct": 0.28
        },
        {
          "pokemon_name": "Ekans",
          "usage_count": 28,
          "usage_pct": 1.06
        },
        {
          "pokemon_name": "Elekid",
          "usage_count": 723,
          "usage_pct": 26.96
        },
        {
          "pokemon_name": "Fidough",
          "usage_count": 0,
          "usage_pct": 0.01
        },
        {
          "pokemon_name": "Flabebe",
          "usage_count": 13,
          "usage_pct": 0.49
        },
        {
          "pokemon_name": "Fletchling",
          "usage_count": 27,
          "usage_pct": 1.0
        },
        {
          "pokemon_name": "Foongus",
          "usage_count": 1068,
          "usage_pct": 39.9
        },
        {
          "pokemon_name": "Froakie",
          "usage_count": 15,
          "usage_pct": 0.52
        },
        {
          "pokemon_name": "Fuecoco",
          "usage_count": 3,
          "usage_pct": 0.12
        },
        {
          "pokemon_name": "Geodude",
          "usage_count": 1,
          "usage_pct": 0.04
        },
        {
          "pokemon_name": "Geodude-Alola",
          "usage_count": 1,
          "usage_pct": 0.05
        },
        {
          "pokemon_name": "Gible",
          "usage_count": 27,
          "usage_pct": 1.04
        },
        {
          "pokemon_name": "Gimmighoul",
          "usage_count": 0,
          "usage_pct": 0.01
        },
        {
          "pokemon_name": "Gimmighoul-Roaming",
          "usage_count": 23,
          "usage_pct": 0.86
        },
        {
          "pokemon_name": "Glimmet",
          "usage_count": 645,
          "usage_pct": 24.3
        },
        {
          "pokemon_name": "Gothita",
          "usage_count": 304,
          "usage_pct": 11.5
        },
        {
          "pokemon_name": "Greavard",
          "usage_count": 30,
          "usage_pct": 1.17
        },
        {
          "pokemon_name": "Grimer",
          "usage_count": 12,
          "usage_pct": 0.45
        },
        {
          "pokemon_name": "Grimer-Alola",
          "usage_count": 21,
          "usage_pct": 0.77
        },
        {
          "pokemon_name": "Grookey",
          "usage_count": 288,
          "usage_pct": 10.73
        },
        {
          "pokemon_name": "Growlithe-Hisui",
          "usage_count": 119,
          "usage_pct": 4.59
        },
        {
          "pokemon_name": "Hippopotas",
          "usage_count": 8,
          "usage_pct": 0.32
        },
        {
          "pokemon_name": "Horsea",
          "usage_count": 10,
          "usage_pct": 0.41
        },
        {
          "pokemon_name": "Houndour",
          "usage_count": 51,
          "usage_pct": 1.81
        },
        {
          "pokemon_name": "Impidimp",
          "usage_count": 145,
          "usage_pct": 5.57
        },
        {
          "pokemon_name": "Jangmo-o",
          "usage_count": 9,
          "usage_pct": 0.36
        },
        {
          "pokemon_name": "Joltik",
          "usage_count": 2,
          "usage_pct": 0.09
        },
        {
          "pokemon_name": "Koffing",
          "usage_count": 131,
          "usage_pct": 5.05
        },
        {
          "pokemon_name": "Larvesta",
          "usage_count": 124,
          "usage_pct": 4.63
        },
        {
          "pokemon_name": "Larvitar",
          "usage_count": 2,
          "usage_pct": 0.06
        },
        {
          "pokemon_name": "Litleo",
          "usage_count": 2,
          "usage_pct": 0.08
        },
        {
          "pokemon_name": "Litten",
          "usage_count": 32,
          "usage_pct": 1.15
        },
        {
          "pokemon_name": "Magnemite",
          "usage_count": 17,
          "usage_pct": 0.61
        },
        {
          "pokemon_name": "Mareanie",
          "usage_count": 558,
          "usage_pct": 21.23
        },
        {
          "pokemon_name": "Maschiff",
          "usage_count": 0,
          "usage_pct": 0.01
        },
        {
          "pokemon_name": "Meowth",
          "usage_count": 72,
          "usage_pct": 2.71
        },
        {
          "pokemon_name": "Meowth-Alola",
          "usage_count": 3,
          "usage_pct": 0.11
        },
        {
          "pokemon_name": "Meowth-Galar",
          "usage_count": 1,
          "usage_pct": 0.04
        },
        {
          "pokemon_name": "Mienfoo",
          "usage_count": 2207,
          "usage_pct": 83.22
        },
        {
          "pokemon_name": "Minccino",
          "usage_count": 174,
          "usage_pct": 6.7
        },
        {
          "pokemon_name": "Mudbray",
          "usage_count": 1124,
          "usage_pct": 42.66
        },
        {
          "pokemon_name": "Munchlax",
          "usage_count": 56,
          "usage_pct": 2.14
        },
        {
          "pokemon_name": "Nosepass",
          "usage_count": 0,
          "usage_pct": 0.01
        },
        {
          "pokemon_name": "Numel",
          "usage_count": 112,
          "usage_pct": 4.29
        },
        {
          "pokemon_name": "Nymble",
          "usage_count": 88,
          "usage_pct": 3.3
        },
        {
          "pokemon_name": "Oddish",
          "usage_count": 5,
          "usage_pct": 0.17
        },
        {
          "pokemon_name": "Oshawott",
          "usage_count": 1,
          "usage_pct": 0.03
        },
        {
          "pokemon_name": "Pawniard",
          "usage_count": 109,
          "usage_pct": 4.11
        },
        {
          "pokemon_name": "Phanpy",
          "usage_count": 1,
          "usage_pct": 0.04
        },
        {
          "pokemon_name": "Phantump",
          "usage_count": 7,
          "usage_pct": 0.27
        },
        {
          "pokemon_name": "Pikipek",
          "usage_count": 18,
          "usage_pct": 0.67
        },
        {
          "pokemon_name": "Pineco",
          "usage_count": 1,
          "usage_pct": 0.04
        },
        {
          "pokemon_name": "Poliwag",
          "usage_count": 7,
          "usage_pct": 0.29
        },
        {
          "pokemon_name": "Poltchageist",
          "usage_count": 1,
          "usage_pct": 0.04
        },
        {
          "pokemon_name": "Psyduck",
          "usage_count": 4,
          "usage_pct": 0.15
        },
        {
          "pokemon_name": "Quaxly",
          "usage_count": 38,
          "usage_pct": 1.43
        },
        {
          "pokemon_name": "Rhyhorn",
          "usage_count": 2,
          "usage_pct": 0.07
        },
        {
          "pokemon_name": "Riolu",
          "usage_count": 14,
          "usage_pct": 0.51
        },
        {
          "pokemon_name": "Rowlet",
          "usage_count": 6,
          "usage_pct": 0.22
        },
        {
          "pokemon_name": "Salandit",
          "usage_count": 53,
          "usage_pct": 2.0
        },
        {
          "pokemon_name": "Sandile",
          "usage_count": 35,
          "usage_pct": 1.29
        },
        {
          "pokemon_name": "Sandshrew",
          "usage_count": 27,
          "usage_pct": 1.01
        },
        {
          "pokemon_name": "Sandshrew-Alola",
          "usage_count": 550,
          "usage_pct": 20.77
        },
        {
          "pokemon_name": "Sandygast",
          "usage_count": 4,
          "usage_pct": 0.16
        },
        {
          "pokemon_name": "Scorbunny",
          "usage_count": 24,
          "usage_pct": 0.9
        },
        {
          "pokemon_name": "Shellder",
          "usage_count": 496,
          "usage_pct": 18.69
        },
        {
          "pokemon_name": "Shellos",
          "usage_count": 143,
          "usage_pct": 5.31
        },
        {
          "pokemon_name": "Shroodle",
          "usage_count": 44,
          "usage_pct": 1.67
        },
        {
          "pokemon_name": "Shroomish",
          "usage_count": 15,
          "usage_pct": 0.59
        },
        {
          "pokemon_name": "Shuppet",
          "usage_count": 1,
          "usage_pct": 0.04
        },
        {
          "pokemon_name": "Silicobra",
          "usage_count": 10,
          "usage_pct": 0.39
        },
        {
          "pokemon_name": "Skiddo",
          "usage_count": 7,
          "usage_pct": 0.26
        },
        {
          "pokemon_name": "Skrelp",
          "usage_count": 3,
          "usage_pct": 0.11
        },
        {
          "pokemon_name": "Slowpoke",
          "usage_count": 87,
          "usage_pct": 3.32
        },
        {
          "pokemon_name": "Slowpoke-Galar",
          "usage_count": 1,
          "usage_pct": 0.04
        },
        {
          "pokemon_name": "Slugma",
          "usage_count": 0,
          "usage_pct": 0.01
        },
        {
          "pokemon_name": "Snom",
          "usage_count": 0,
          "usage_pct": 0.01
        },
        {
          "pokemon_name": "Snover",
          "usage_count": 53,
          "usage_pct": 2.03
        },
        {
          "pokemon_name": "Snubbull",
          "usage_count": 35,
          "usage_pct": 1.36
        },
        {
          "pokemon_name": "Solosis",
          "usage_count": 2,
          "usage_pct": 0.09
        },
        {
          "pokemon_name": "Squirtle",
          "usage_count": 44,
          "usage_pct": 1.68
        },
        {
          "pokemon_name": "Stunky",
          "usage_count": 398,
          "usage_pct": 14.91
        },
        {
          "pokemon_name": "Teddiursa",
          "usage_count": 7,
          "usage_pct": 0.28
        },
        {
          "pokemon_name": "Tentacool",
          "usage_count": 159,
          "usage_pct": 6.01
        },
        {
          "pokemon_name": "Timburr",
          "usage_count": 37,
          "usage_pct": 1.4
        },
        {
          "pokemon_name": "Tinkatink",
          "usage_count": 661,
          "usage_pct": 24.89
        },
        {
          "pokemon_name": "Toedscool",
          "usage_count": 708,
          "usage_pct": 26.84
        },
        {
          "pokemon_name": "Totodile",
          "usage_count": 1,
          "usage_pct": 0.04
        },
        {
          "pokemon_name": "Trapinch",
          "usage_count": 281,
          "usage_pct": 10.54
        },
        {
          "pokemon_name": "Turtwig",
          "usage_count": 10,
          "usage_pct": 0.4
        },
        {
          "pokemon_name": "Varoom",
          "usage_count": 16,
          "usage_pct": 0.59
        },
        {
          "pokemon_name": "Venonat",
          "usage_count": 17,
          "usage_pct": 0.63
        },
        {
          "pokemon_name": "Voltorb",
          "usage_count": 2,
          "usage_pct": 0.08
        },
        {
          "pokemon_name": "Vullaby",
          "usage_count": 1852,
          "usage_pct": 70.06
        },
        {
          "pokemon_name": "Wattrel",
          "usage_count": 84,
          "usage_pct": 3.24
        },
        {
          "pokemon_name": "Wiglett",
          "usage_count": 1,
          "usage_pct": 0.02
        },
        {
          "pokemon_name": "Wingull",
          "usage_count": 102,
          "usage_pct": 3.91
        },
        {
          "pokemon_name": "Yungoos",
          "usage_count": 1,
          "usage_pct": 0.02
        },
        {
          "pokemon_name": "Zorua",
          "usage_count": 1,
          "usage_pct": 0.03
        },
        {
          "pokemon_name": "Zorua-Hisui",
          "usage_count": 161,
          "usage_pct": 6.06
        }
      ]
    }
  }
}